Workbook

Sheet How to use
A1: Manual analysis helper (auto-import) — Academic OSPO Readiness Survey
A3: Paste your LimeSurvey responses export once; the analysis fills in. No typing numbers.
A5: Steps
A6: 1. In LimeSurvey: Results > Export results. Format = Excel; Headings = 'Question code & question
A7: text'; Strip HTML = On; Completion state = All responses; Responses = Full answers.
A8: (The sheet automatically counts only completed responses for the percentages.)
A9: 2. Open that export, select all (Ctrl+A), copy (Ctrl+C).
A10: 3. On the 'Data (paste export here)' tab: select all (Ctrl+A), Delete, click A1, paste (Ctrl+V).
A11: 4. Read 'Service summary' and 'Level summary'. (Recalc with Ctrl+Shift+F9 if needed.)
A13: Check it worked
A14: On 'Item results (auto)', the 'Check' column shows ✓ when an item's expected wording is found
A15: in your pasted export. An ✗ means the wording was edited (or the column is missing): the result may
... A22: This sheet uses fully completed responses only. For a richer view that also uses partial responses (e.g. people who answered the first parts and stopped), use the notebook.

Sheet Data (paste export here)
A1: id. Response ID | B1: submitdate. Date submitted | C1: lastpage. Last page | D1: startlanguage. Start language | E1: seed. Seed | F1: Q10. What is your role at Example University? | G1: Q10[comment]. What is your role at Example University? [Comment] | H1: Q20. How important is open source to Example University's mission? | I1: Q21[SQ001]. Why is open source important to your work? [Reduces vendor lock-in] | J1: Q21[SQ002]. Why is open source important to your work? [Lowers costs] | K1: Q21[SQ003]. Why is open source important to your work? [Enables collaboration across the research and education community] | L1: Q21[SQ004]. Why is open source important to your work? [Supports transparency and trust] | M1: Q21[SQ005]. Why is open source important to your work? [Accelerates innovation] | N1: Q21[SQ006]. Why is open source important to your work? [Fulfils funder or regulatory requirements] | O1: Q21[SQ007]. Why is open source important to your work? [Aligns with digital-sovereignty or institutional-autonomy goals] | P1: Q21[SQ008]. Why is open source important to your work? [None — open source is not important to my work] | Q1: Q21[other]. Why is open source important to your work? [Other] | R1: Q22. How confident are you in your knowledge of open source practices relevant to your role? | S1: INTRO3. Over the next several pages we ask what Example University already does with open source: its policies, security, contributions, and similar work. Each page covers one topic.Answer from your own knowledge. Tick what you know is already in place, and if you haven't heard of something, leave it unticked instead of guessing. Not knowing is a fine answer. | T1: Q300[SQ001]. Tick the ones you know are already in place. [Has an open source program office (OSPO) or equivalent function] | U1: Q300[SQ002]. Tick the ones you know are already in place. [Has an open source use policy] | V1: Q300[SQ003]. Tick the ones you know are already in place. [Has a defined process for using open source software] | W1: Q300[SQ004]. Tick the ones you know are already in place. [Provides staff with guidance on the responsible use of open source AI] | X1: Q300[SQ005]. Tick the ones you know are already in place. [None of the above] | Y1: Q301. Where is support for "policy and open source program office" activities currently available at Example University? | Z1: Q310[SQ001]. Tick the ones you know are already in place. [Has standardized controls around open source use] | AA1: Q310[SQ002]. Tick the ones you know are already in place. [Has an automated process for managing open source IP / license compliance] | AB1: Q310[SQ003]. Tick the ones you know are already in place. [Includes open source risk management in its compliance policy] | AC1: Q310[SQ004]. Tick the ones you know are already in place. [Engages its technology-transfer or knowledge-exchange office when releasing or licensing open source software] | AD1: Q310[SQ005]. Tick the ones you know are already in place. [Provides internal license-compliance training] | AE1: Q310[SQ006]. Tick the ones you know are already in place. [Addresses AI-generated code (licensing, attribution, and IP) in its open source or compliance policy] | AF1: Q310[SQ007]. Tick the ones you know are already in place. [None of the above] | AG1: Q311. Where is support for "compliance and risk" activities currently available at Example University? | AH1: Q320[SQ001]. Tick the ones you know are already in place. [Uses code-scanning tools to audit software composition and dependencies] | AI1: Q320[SQ002]. Tick the ones you know are already in place. [Runs penetration tests and periodic threat assessments for open source software] | AJ1: Q320[SQ003]. Tick the ones you know are already in place. [Provides security training for teams working on open source software] | AK1: Q320[SQ004]. Tick the ones you know are already in place. [None of the above] | AL1: Q321. Where is support for "security and supply chain" activities currently available at Example University? | AM1: Q330[SQ001]. Tick the ones you know are already in place. [Has a process to choose between open source alternatives] | AN1: Q330[SQ002]. Tick the ones you know are already in place. [Prefers open source solutions over proprietary software where appropriate] | AO1: Q330[SQ003]. Tick the ones you know are already in place. [Applies open source criteria in procurement decisions] | AP1: Q330[SQ004]. Tick the ones you know are already in place. [Has a procurement process that doesn't hinder open source use] | AQ1: Q330[SQ005]. Tick the ones you know are already in place. [Maintains a software asset registry / inventory] | AR1: Q330[SQ006]. Tick the ones you know are already in place. [Provides internal training on open source usage policies and procedures] | AS1: Q330[SQ007]. Tick the ones you know are already in place. [None of the above] | AT1: Q331. Where is support for "open source selection, use, and procurement" activities currently available at Example University? | AU1: Q340[SQ001]. Tick the ones you know are already in place. [Has policies to govern contribution to open source ecosystems] | AV1: Q340[SQ002]. Tick the ones you know are already in place. [Has a clear policy for how staff publish or contribute to open source projects] | AW1: Q340[SQ003]. Tick the ones you know are already in place. [Has processes that support open source contribution] | AX1: Q340[SQ004]. Tick the ones you know are already in place. [Has a review process for code and non-code contributions] | AY1: Q340[SQ005]. Tick the ones you know are already in place. [Has a lifecycle process for engaging with open source projects] | AZ1: Q340[SQ006]. Tick the ones you know are already in place. [None of the above] | BA1: Q341. Where is support for "open source contribution" activities currently available at Example University? | BB1: Q350[SQ001]. Tick the ones you know are already in place. [Promotes and rewards contribution to open source projects] | BC1: Q350[SQ002]. Tick the ones you know are already in place. [Tracks staff or members' open source contributions] | BD1: Q350[SQ003]. Tick the ones you know are already in place. [Maintains an inventory of open source projects created within Example University] | BE1: Q350[SQ004]. Tick the ones you know are already in place. [Fosters outreach for the visibility of its open source projects] | BF1: Q350[SQ005]. Tick the ones you know are already in place. [Engages marketing / communications in open source publishing efforts] | BG1: Q350[SQ006]. Tick the ones you know are already in place. [None of the above] | BH1: Q351. Where is support for "community and outreach" activities currently available at Example University? | BI1: Q360[SQ001]. Tick the ones you know are already in place. [Has a defined process for open-sourcing internal projects] | BJ1: Q360[SQ002]. Tick the ones you know are already in place. [Holds maintainer status on one or more open source projects] | BK1: Q360[SQ003]. Tick the ones you know are already in place. [Measures the health of the open source projects it maintains] | BL1: Q360[SQ004]. Tick the ones you know are already in place. [Tracks the adoption and impact of its research software (downloads, citations, reuse)] | BM1: Q360[SQ005]. Tick the ones you know are already in place. [Is a member of one or more software foundations] | BN1: Q360[SQ006]. Tick the ones you know are already in place. [Tracks KPIs / metrics around its open source foundation engagement] | BO1: Q360[SQ007]. Tick the ones you know are already in place. [Provides shared development infrastructure (e.g. code hosting, CI/CD) for its open source projects] | BP1: Q360[SQ008]. Tick the ones you know are already in place. [Offers compute or storage resources to support open source development] | BQ1: Q360[SQ009]. Tick the ones you know are already in place. [None of the above] | BR1: Q361. Where is support for "hosting and maintenance" activities currently available at Example University? | BS1: Q370[SQ001]. Tick the ones you know are already in place. [Management recognises the benefits of open source] | BT1: Q370[SQ002]. Tick the ones you know are already in place. [Management understands the cost savings of open source] | BU1: Q370[SQ003]. Tick the ones you know are already in place. [Defines goals and objectives in an open source strategy] | BV1: Q370[SQ004]. Tick the ones you know are already in place. [Connects its open source work to its research mission and impact] | BW1: Q370[SQ005]. Tick the ones you know are already in place. [Has a strategy for the financial sustainability of its open source projects] | BX1: Q370[SQ006]. Tick the ones you know are already in place. [Allocates dedicated budget or funding to sustain and maintain its open source projects] | BY1: Q370[SQ007]. Tick the ones you know are already in place. [Formally allocates staff time to open source maintenance and contribution] | BZ1: Q370[SQ008]. Tick the ones you know are already in place. [None of the above] | CA1: Q371. Where is support for "leadership and strategy" activities currently available at Example University? | CB1: INTRO4. Example University wants to do a better job of supporting open source work, and is working out how. The pages that follow list kinds of support it might offer, grouped by topic.Start with your own work. Tick what would help you, and leave the rest. You don't need to weigh up what other people might want. | CC1: Q400[SQ001]. Tick the support you'd find valuable for your open source work. [Legal and open source licensing advice and support] | CD1: Q400[SQ002]. Tick the support you'd find valuable for your open source work. [Advice on security management] | CE1: Q400[SQ003]. Tick the support you'd find valuable for your open source work. [Advice on dependency management] | CF1: Q400[SQ004]. Tick the support you'd find valuable for your open source work. [Assessing vendor open source obligations (e.g. CRA compliance, software bills of materials)] | CG1: Q400[SQ005]. Tick the support you'd find valuable for your open source work. [Grant compliance with respect to open source requirements] | CH1: Q400[SQ006]. Tick the support you'd find valuable for your open source work. [Policy recommendations and best practices around open source AI] | CI1: Q400[SQ007]. Tick the support you'd find valuable for your open source work. [None of the above] | CJ1: Q401. Is there any other "legal, compliance, and risk" support that would be valuable to you? | CK1: Q410[SQ001]. Tick the support you'd find valuable for your open source work. [Guidelines or policies for using open source software within Example University] | CL1: Q410[SQ002]. Tick the support you'd find valuable for your open source work. [Guidelines or policies for procuring open source software] | CM1: Q410[SQ003]. Tick the support you'd find valuable for your open source work. [A curated catalogue or directory of open source tools relevant to Example University's community] | CN1: Q410[SQ004]. Tick the support you'd find valuable for your open source work. [None of the above] | CO1: Q411. Is there any other "open source selection, use, and procurement" support that would be valuable to you? | CP1: Q420[SQ001]. Tick the support you'd find valuable for your open source work. [Guidelines or policies on managing and maintaining an open source project] | CQ1: Q420[SQ002]. Tick the support you'd find valuable for your open source work. [Guidance on transitioning an internal project to open source] | CR1: Q420[SQ003]. Tick the support you'd find valuable for your open source work. [Support writing documentation for open source projects] | CS1: Q420[SQ004]. Tick the support you'd find valuable for your open source work. [An assessment or audit of my open source project's community health and contributor readiness] | CT1: Q420[SQ005]. Tick the support you'd find valuable for your open source work. [None of the above] | CU1: Q421. Is there any other "open source project creation and maintenance" support that would be valuable to you? | CV1: Q430[SQ001]. Tick the support you'd find valuable for your open source work. [An open source community of practice, discussion group, or learning group] | CW1: Q430[SQ002]. Tick the support you'd find valuable for your open source work. [Mentorship on open source practices for myself or my team] | CX1: Q430[SQ003]. Tick the support you'd find valuable for your open source work. [Mentoring programmes to bring new people into my project] | CY1: Q430[SQ004]. Tick the support you'd find valuable for your open source work. [Training, workshops, and educational materials on open source topics and tools (e.g. programming languages, popular packages)] | CZ1: Q430[SQ005]. Tick the support you'd find valuable for your open source work. [None of the above] | DA1: Q431. Is there any other "community and mentoring" support that would be valuable to you? | DB1: Q440[SQ001]. Tick the support you'd find valuable for your open source work. [Support identifying potential funding sources] | DC1: Q440[SQ002]. Tick the support you'd find valuable for your open source work. [Support with grant applications and grant writing] | DD1: Q440[SQ003]. Tick the support you'd find valuable for your open source work. [Dedicated grants or funding from Example University to sustain and maintain my open source projects] | DE1: Q440[SQ004]. Tick the support you'd find valuable for your open source work. [Help developing a sustainable business or funding model for my open source project] | DF1: Q440[SQ005]. Tick the support you'd find valuable for your open source work. [None of the above] | DG1: Q441. Is there any other "funding and sustainability" support that would be valuable to you? | DH1: Q450[SQ001]. Tick the support you'd find valuable for your open source work. [Hosted development tools and infrastructure for open source software] | DI1: Q450[SQ002]. Tick the support you'd find valuable for your open source work. [Support creating containers (e.g. Docker) for my open source software] | DJ1: Q450[SQ003]. Tick the support you'd find valuable for your open source work. [Access to CPU or high-performance computing resources at low or no cost] | DK1: Q450[SQ004]. Tick the support you'd find valuable for your open source work. [Access to GPU resources (e.g. for AI/ML workloads) at low or no cost] | DL1: Q450[SQ005]. Tick the support you'd find valuable for your open source work. [Access to data storage infrastructure at low or no cost] | DM1: Q450[SQ006]. Tick the support you'd find valuable for your open source work. [Access to CI/CD pipelines and automated testing infrastructure at low or no cost] | DN1: Q450[SQ007]. Tick the support you'd find valuable for your open source work. [Access to hosted test or staging environments at low or no cost] | DO1: Q450[SQ008]. Tick the support you'd find valuable for your open source work. [Access to licensed software, SaaS tools, or development platforms at low or no cost] | DP1: Q450[SQ009]. Tick the support you'd find valuable for your open source work. [None of the above] | DQ1: Q451. Is there any other "tools and compute resources" support that would be valuable to you? | DR1: Q460[SQ001]. Tick the support you'd find valuable for your open source work. [Internal advocacy support to secure organisational buy-in for open source] | DS1: Q460[SQ002]. Tick the support you'd find valuable for your open source work. [Marketing and promotion support for my open source projects] | DT1: Q460[SQ003]. Tick the support you'd find valuable for your open source work. [Help hosting, planning, or co-sponsoring open source events (e.g. conferences and hackathons)] | DU1: Q460[SQ004]. Tick the support you'd find valuable for your open source work. [Support building partnerships and collaborations with external organisations] | DV1: Q460[SQ005]. Tick the support you'd find valuable for your open source work. [Support communicating or measuring the societal impact of my open source work] | DW1: Q460[SQ006]. Tick the support you'd find valuable for your open source work. [None of the above] | DX1: Q461. Is there any other "advocacy and outreach" support that would be valuable to you? | DY1: Q50. If you are willing, please tell us about your background with open source. The next questions are optional. | DZ1: Q51. Would you be willing to answer a few optional questions about your personal experience with open source? | EA1: Q52[SQ001]. People participate in open source in different ways. Which of the following activities do you engage in? [Follow updates and discussions of open source projects] | EB1: Q52[SQ002]. People participate in open source in different ways. Which of the following activities do you engage in? [Use open source applications] | EC1: Q52[SQ003]. People participate in open source in different ways. Which of the following activities do you engage in? [Use open source dependencies in other projects] | ED1: Q52[SQ004]. People participate in open source in different ways. Which of the following activities do you engage in? [Participate in open source development (feature requests, filing bugs, contributing docs or code, maintenance, community management, etc.)] | EE1: Q52[SQ005]. People participate in open source in different ways. Which of the following activities do you engage in? [None of the above] | EF1: Q52[other]. People participate in open source in different ways. Which of the following activities do you engage in? [Other] | EG1: Q53[SQ001]. Which of the following activities do you take part in? [Contribute code] | EH1: Q53[SQ002]. Which of the following activities do you take part in? [Contribute documentation] | EI1: Q53[SQ003]. Which of the following activities do you take part in? [Maintain a project (review and merge contributions, manage releases)] | EJ1: Q53[SQ004]. Which of the following activities do you take part in? [Report or document bugs and unexpected behaviours] | EK1: Q53[SQ005]. Which of the following activities do you take part in? [Offer ideas for new features] | EL1: Q53[SQ006]. Which of the following activities do you take part in? [Perform organisational / administrative functions (manage mailing lists, organise events)] | EM1: Q53[SQ007]. Which of the following activities do you take part in? [Grow a project (marketing, outreach, sales, growth, community management)] | EN1: Q53[SQ008]. Which of the following activities do you take part in? [Develop open source policy] | EO1: Q53[SQ009]. Which of the following activities do you take part in? [None of the above] | EP1: Q54[SQ001]. Which of these open source contributor roles has ever applied to you? [Maintainer: authoring much or most of the codebase / designs for at least one open source product intended for public reuse] | EQ1: Q54[SQ002]. Which of these open source contributor roles has ever applied to you? [Contributor: contributing smaller amounts of code or design, e.g. fixing bugs or adding features] | ER1: Q54[SQ003]. Which of these open source contributor roles has ever applied to you? [Bug / issue reporter: reporting bugs or issues, or requesting new features] | ES1: Q54[SQ004]. Which of these open source contributor roles has ever applied to you? [Supervisor: guiding the strategic vision of at least one project, and/or acquiring funding for it] | ET1: Q54[SQ005]. Which of these open source contributor roles has ever applied to you? [IT / systems administrator: providing technical infrastructure for open source developers] | EU1: Q54[SQ006]. Which of these open source contributor roles has ever applied to you? [UI / UX designer: creating user-centered interfaces and experiences] | EV1: Q54[SQ007]. Which of these open source contributor roles has ever applied to you? [Community manager: engaging the community, facilitating communication, encouraging contributions] | EW1: Q54[SQ008]. Which of these open source contributor roles has ever applied to you? [Technical support: assisting users through forums, email, or other channels] | EX1: Q54[SQ009]. Which of these open source contributor roles has ever applied to you? [Educator: creating documentation, tutorials, articles, or other learning materials] | EY1: Q54[SQ010]. Which of these open source contributor roles has ever applied to you? [None of the above] | EZ1: Q54[other]. Which of these open source contributor roles has ever applied to you? [Other] | FA1: Q55[SQ001]. Why do you participate in open source projects? [My work duties include contributing to open source projects] | FB1: Q55[SQ002]. Why do you participate in open source projects? [To carry out other work duties, but I am not required or expected to do so] | FC1: Q55[SQ003]. Why do you participate in open source projects? [To improve the tools in my field] | FD1: Q55[SQ004]. Why do you participate in open source projects? [To customise existing tools for my specific needs] | FE1: Q55[SQ005]. Why do you participate in open source projects? [To build a network of peers] | FF1: Q55[SQ006]. Why do you participate in open source projects? [To give back to the open source community] | FG1: Q55[SQ007]. Why do you participate in open source projects? [To improve my skills] | FH1: Q55[SQ008]. Why do you participate in open source projects? [Because it's fun] | FI1: Q55[SQ009]. Why do you participate in open source projects? [None of the above] | FJ1: Q55[other]. Why do you participate in open source projects? [Other] | FK1: Q56[SQ001]. What category(ies) of open source projects have you participated in? [Hardware: physical devices used for research (cameras, robots, behavioural rigs) and associated code] | FL1: Q56[SQ002]. What category(ies) of open source projects have you participated in? [Applications: standalone software systems designed to be used as-is] | FM1: Q56[SQ003]. What category(ies) of open source projects have you participated in? [Plug-ins or extensions: add-ons that extend existing software or platforms] | FN1: Q56[SQ004]. What category(ies) of open source projects have you participated in? [Libraries, packages, or frameworks: reusable code distributed through established community mechanisms] | FO1: Q56[SQ005]. What category(ies) of open source projects have you participated in? [Automation scripts: scripts or tools to automate workflows or repetitive tasks] | FP1: Q56[SQ006]. What category(ies) of open source projects have you participated in? [Website code: back-end or front-end website components] | FQ1: Q56[SQ007]. What category(ies) of open source projects have you participated in? [None of the above] | FR1: Q56[other]. What category(ies) of open source projects have you participated in? [Other] | FS1: Q57[SQ001]. Which of the following challenges have you encountered while participating in open source projects? [Limited time for writing new code] | FT1: Q57[SQ002]. Which of the following challenges have you encountered while participating in open source projects? [Limited time for writing documentation] | FU1: Q57[SQ003]. Which of the following challenges have you encountered while participating in open source projects? [Managing issues and pull requests] | FV1: Q57[SQ004]. Which of the following challenges have you encountered while participating in open source projects? [Attracting users and/or contributors] | FW1: Q57[SQ005]. Which of the following challenges have you encountered while participating in open source projects? [Receiving recognition for my contributions] | FX1: Q57[SQ006]. Which of the following challenges have you encountered while participating in open source projects? [Finding and hiring qualified personnel] | FY1: Q57[SQ007]. Which of the following challenges have you encountered while participating in open source projects? [Managing security risks] | FZ1: Q57[SQ008]. Which of the following challenges have you encountered while participating in open source projects? [Finding a community of peers who share my interests] | GA1: Q57[SQ009]. Which of the following challenges have you encountered while participating in open source projects? [Finding mentors] | GB1: Q57[SQ010]. Which of the following challenges have you encountered while participating in open source projects? [Finding time to educate myself] | GC1: Q57[SQ011]. Which of the following challenges have you encountered while participating in open source projects? [Identifying helpful educational resources] | GD1: Q57[SQ012]. Which of the following challenges have you encountered while participating in open source projects? [Navigating licensing and other legal issues] | GE1: Q57[SQ013]. Which of the following challenges have you encountered while participating in open source projects? [Identifying potential funding sources for my open source projects] | GF1: Q57[SQ014]. Which of the following challenges have you encountered while participating in open source projects? [Securing funding for my open source projects] | GG1: Q57[SQ015]. Which of the following challenges have you encountered while participating in open source projects? [None of the above] | GH1: Q58. Other challenges | GI1: Q70. (Optional) Is there anything important we missed, or anything you'd like to clarify?
A2: 1 | B2: 1980-01-01 00:00:00 | C2: 25 | D2: en | E2: 699969027 | F2: Student (graduate or undergraduate) | H2: Somewhat important | I2: No | J2: No | K2: No | L2: No | M2: Yes | N2: Yes | O2: Yes | P2: No | R2: Confident | T2: Yes | U2: No | V2: Yes | W2: No | X2: No | Z2: N/A | AA2: N/A | AB2: N/A | AC2: N/A | AD2: N/A | AE2: N/A | AF2: Yes | AH2: Yes | AI2: No | AJ2: Yes | AK2: No | AM2: No | AN2: Yes | AO2: No | AP2: Yes | AQ2: No | AR2: No | AS2: No | AU2: No | AV2: No | AW2: No | AX2: No | AY2: Yes | AZ2: No | BB2: Yes | BC2: Yes | BD2: No | BE2: No | BF2: No | BG2: No | BI2: No | BJ2: No | BK2: No | BL2: No | BM2: Yes | BN2: No | BO2: Yes | BP2: No | BQ2: No | BS2: No | BT2: No | BU2: No | BV2: No | BW2: No | BX2: No | BY2: Yes | BZ2: No | CC2: Yes | CD2: Yes | CE2: No | CF2: No | CG2: Yes | CH2: No | CI2: No | CK2: Yes | CL2: No | CM2: Yes | CN2: No | CP2: Yes | CQ2: Yes | CR2: No | CS2: No | CT2: No | CV2: No | CW2: No | CX2: No | CY2: Yes | CZ2: No | DB2: No | DC2: Yes | DD2: No | DE2: Yes | DF2: No | DH2: No | DI2: No | DJ2: No | DK2: No | DL2: No | DM2: Yes | DN2: No | DO2: No | DP2: No | DR2: No | DS2: No | DT2: No | DU2: No | DV2: Yes | DW2: No | DZ2: No | EA2: N/A | EB2: N/A | EC2: N/A | ED2: N/A | EE2: N/A | EG2: N/A | EH2: N/A | EI2: N/A | EJ2: N/A | EK2: N/A | EL2: N/A | EM2: N/A | EN2: N/A | EO2: N/A | EP2: N/A | EQ2: N/A | ER2: N/A | ES2: N/A | ET2: N/A | EU2: N/A | EV2: N/A | EW2: N/A | EX2: N/A | EY2: N/A | FA2: N/A | FB2: N/A | FC2: N/A | FD2: N/A | FE2: N/A | FF2: N/A | FG2: N/A | FH2: N/A | FI2: N/A | FK2: N/A | FL2: N/A | FM2: N/A | FN2: N/A | FO2: N/A | FP2: N/A | FQ2: N/A | FS2: N/A | FT2: N/A | FU2: N/A | FV2: N/A | FW2: N/A | FX2: N/A | FY2: N/A | FZ2: N/A | GA2: N/A | GB2: N/A | GC2: N/A | GD2: N/A | GE2: N/A | GF2: N/A | GG2: N/A
A3: 2 | B3: 1980-01-01 00:00:00 | C3: 25 | D3: en | E3: 1478178211 | F3: Faculty / Academic staff | H3: Not important | I3: N/A | J3: N/A | K3: N/A | L3: N/A | M3: N/A | N3: N/A | O3: N/A | P3: N/A | R3: Somewhat confident | T3: N/A | U3: N/A | V3: N/A | W3: N/A | X3: Yes | Y3: Scout response | Z3: N/A | AA3: N/A | AB3: N/A | AC3: N/A | AD3: N/A | AE3: N/A | AF3: Yes | AG3: Scout response | AH3: N/A | AI3: N/A | AJ3: N/A | AK3: Yes | AL3: Scout response | AM3: N/A | AN3: N/A | AO3: N/A | AP3: N/A | AQ3: N/A | AR3: N/A | AS3: Yes | AT3: Scout response | AU3: N/A | AV3: N/A | AW3: N/A | AX3: N/A | AY3: N/A | AZ3: Yes | BA3: Scout response | BB3: N/A | BC3: N/A | BD3: N/A | BE3: N/A | BF3: N/A | BG3: Yes | BH3: Scout response | BI3: N/A | BJ3: N/A | BK3: N/A | BL3: N/A | BM3: N/A | BN3: N/A | BO3: N/A | BP3: N/A | BQ3: Yes | BR3: Scout response | BS3: N/A | BT3: N/A | BU3: N/A | BV3: N/A | BW3: N/A | BX3: N/A | BY3: N/A | BZ3: Yes | CA3: Scout response | CC3: N/A | CD3: N/A | CE3: N/A | CF3: N/A | CG3: N/A | CH3: N/A | CI3: Yes | CJ3: Scout response | CK3: N/A | CL3: N/A | CM3: N/A | CN3: Yes | CO3: Scout response | CP3: N/A | CQ3: N/A | CR3: N/A | CS3: N/A | CT3: Yes | CU3: Scout response | CV3: N/A | CW3: N/A | CX3: N/A | CY3: N/A | CZ3: Yes | DA3: Scout response | DB3: N/A | DC3: N/A | DD3: N/A | DE3: N/A | DF3: Yes | DG3: Scout response | DH3: N/A | DI3: N/A | DJ3: N/A | DK3: N/A | DL3: N/A | DM3: N/A | DN3: N/A | DO3: N/A | DP3: Yes | DQ3: Scout response | DR3: N/A | DS3: N/A | DT3: N/A | DU3: N/A | DV3: N/A | DW3: Yes | DX3: Scout response | DZ3: No | EA3: N/A | EB3: N/A | EC3: N/A | ED3: N/A | EE3: N/A | EG3: N/A | EH3: N/A | EI3: N/A | EJ3: N/A | EK3: N/A | EL3: N/A | EM3: N/A | EN3: N/A | EO3: N/A | EP3: N/A | EQ3: N/A | ER3: N/A | ES3: N/A | ET3: N/A | EU3: N/A | EV3: N/A | EW3: N/A | EX3: N/A | EY3: N/A | FA3: N/A | FB3: N/A | FC3: N/A | FD3: N/A | FE3: N/A | FF3: N/A | FG3: N/A | FH3: N/A | FI3: N/A | FK3: N/A | FL3: N/A | FM3: N/A | FN3: N/A | FO3: N/A | FP3: N/A | FQ3: N/A | FS3: N/A | FT3: N/A | FU3: N/A | FV3: N/A | FW3: N/A | FX3: N/A | FY3: N/A | FZ3: N/A | GA3: N/A | GB3: N/A | GC3: N/A | GD3: N/A | GE3: N/A | GF3: N/A | GG3: N/A | GI3: Scout response
A4: 3 | C4: 1 | D4: en | E4: 1521051725 | F4: Faculty / Academic staff | G4: Computer Science Department | H4: Critical | I4: No | J4: No | K4: No | L4: No | M4: No | N4: No | O4: No | P4: No | T4: N/A | U4: N/A | V4: N/A | W4: N/A | X4: N/A | Z4: N/A | AA4: N/A | AB4: N/A | AC4: N/A | AD4: N/A | AE4: N/A | AF4: N/A | AH4: N/A | AI4: N/A | AJ4: N/A | AK4: N/A | AM4: N/A | AN4: N/A | AO4: N/A | AP4: N/A | AQ4: N/A | AR4: N/A | AS4: N/A | AU4: N/A | AV4: N/A | AW4: N/A | AX4: N/A | AY4: N/A | AZ4: N/A | BB4: N/A | BC4: N/A | BD4: N/A | BE4: N/A | BF4: N/A | BG4: N/A | BI4: N/A | BJ4: N/A | BK4: N/A | BL4: N/A | BM4: N/A | BN4: N/A | BO4: N/A | BP4: N/A | BQ4: N/A | BS4: N/A | BT4: N/A | BU4: N/A | BV4: N/A | BW4: N/A | BX4: N/A | BY4: N/A | BZ4: N/A | CC4: N/A | CD4: N/A | CE4: N/A | CF4: N/A | CG4: N/A | CH4: N/A | CI4: N/A | CK4: N/A | CL4: N/A | CM4: N/A | CN4: N/A | CP4: N/A | CQ4: N/A | CR4: N/A | CS4: N/A | CT4: N/A | CV4: N/A | CW4: N/A | CX4: N/A | CY4: N/A | CZ4: N/A | DB4: N/A | DC4: N/A | DD4: N/A | DE4: N/A | DF4: N/A | DH4: N/A | DI4: N/A | DJ4: N/A | DK4: N/A | DL4: N/A | DM4: N/A | DN4: N/A | DO4: N/A | DP4: N/A | DR4: N/A | DS4: N/A | DT4: N/A | DU4: N/A | DV4: N/A | DW4: N/A | DZ4: N/A | EA4: N/A | EB4: N/A | EC4: N/A | ED4: N/A | EE4: N/A | EG4: N/A | EH4: N/A | EI4: N/A | EJ4: N/A | EK4: N/A | EL4: N/A | EM4: N/A | EN4: N/A | EO4: N/A | EP4: N/A | EQ4: N/A | ER4: N/A | ES4: N/A | ET4: N/A | EU4: N/A | EV4: N/A | EW4: N/A | EX4: N/A | EY4: N/A | FA4: N/A | FB4: N/A | FC4: N/A | FD4: N/A | FE4: N/A | FF4: N/A | FG4: N/A | FH4: N/A | FI4: N/A | FK4: N/A | FL4: N/A | FM4: N/A | FN4: N/A | FO4: N/A | FP4: N/A | FQ4: N/A | FS4: N/A | FT4: N/A | FU4: N/A | FV4: N/A | FW4: N/A | FX4: N/A | FY4: N/A | FZ4: N/A | GA4: N/A | GB4: N/A | GC4: N/A | GD4: N/A | GE4: N/A | GF4: N/A | GG4: N/A
A5: 4 | C5: 1 | D5: en | E5: 1112276437 | I5: N/A | J5: N/A | K5: N/A | L5: N/A | M5: N/A | N5: N/A | O5: N/A | P5: N/A | T5: No | U5: No | V5: No | W5: No | X5: No | Z5: No | AA5: No | AB5: No | AC5: No | AD5: No | AE5: No | AF5: No | AH5: No | AI5: No | AJ5: No | AK5: No | AM5: No | AN5: No | AO5: No | AP5: No | AQ5: No | AR5: No | AS5: No | AU5: No | AV5: No | AW5: No | AX5: No | AY5: No | AZ5: No | BB5: No | BC5: No | BD5: No | BE5: No | BF5: No | BG5: No | BI5: No | BJ5: No | BK5: No | BL5: No | BM5: No | BN5: No | BO5: No | BP5: No | BQ5: No | BS5: No | BT5: No | BU5: No | BV5: No | BW5: No | BX5: No | BY5: No | BZ5: No | CC5: No | CD5: No | CE5: No | CF5: No | CG5: No | CH5: No | CI5: No | CK5: No | CL5: No | CM5: No | CN5: No | CP5: No | CQ5: No | CR5: No | CS5: No | CT5: No | CV5: No | CW5: No | CX5: No | CY5: No | CZ5: No | DB5: No | DC5: No | DD5: No | DE5: No | DF5: No | DH5: No | DI5: No | DJ5: No | DK5: No | DL5: No | DM5: No | DN5: No | DO5: No | DP5: No | DR5: No | DS5: No | DT5: No | DU5: No | DV5: No | DW5: No | DZ5: N/A | EA5: N/A | EB5: N/A | EC5: N/A | ED5: N/A | EE5: N/A | EG5: N/A | EH5: N/A | EI5: N/A | EJ5: N/A | EK5: N/A | EL5: N/A | EM5: N/A | EN5: N/A | EO5: N/A | EP5: N/A | EQ5: N/A | ER5: N/A | ES5: N/A | ET5: N/A | EU5: N/A | EV5: N/A | EW5: N/A | EX5: N/A | EY5: N/A | FA5: N/A | FB5: N/A | FC5: N/A | FD5: N/A | FE5: N/A | FF5: N/A | FG5: N/A | FH5: N/A | FI5: N/A | FK5: N/A | FL5: N/A | FM5: N/A | FN5: N/A | FO5: N/A | FP5: N/A | FQ5: N/A | FS5: N/A | FT5: N/A | FU5: N/A | FV5: N/A | FW5: N/A | FX5: N/A | FY5: N/A | FZ5: N/A | GA5: N/A | GB5: N/A | GC5: N/A | GD5: N/A | GE5: N/A | GF5: N/A | GG5: N/A
A6: 5 | B6: 1980-01-01 00:00:00 | C6: 25 | D6: en | E6: 562588783 | F6: Faculty / Academic staff | G6: Computer Science Department | H6: Critical | I6: No | J6: No | K6: Yes | L6: Yes | M6: Yes | N6: No | O6: No | P6: No | R6: Confident | T6: Yes | U6: Yes | V6: No | W6: No | X6: No | Y6: Our dept has informal practices but nothing coordinated at university level. | Z6: Yes | AA6: Yes | AB6: No | AC6: No | AD6: No | AE6: No | AF6: No | AG6: Our dept has informal practices but nothing coordinated at university level. | AH6: Yes | AI6: Yes | AJ6: No | AK6: No | AL6: Our dept has informal practices but nothing coordinated at university level. | AM6: Yes | AN6: Yes | AO6: No | AP6: No | AQ6: No | AR6: No | AS6: No | AT6: Our dept has informal practices but nothing coordinated at university level. | AU6: Yes | AV6: Yes | AW6: No | AX6: No | AY6: No | AZ6: No | BA6: Our dept has informal practices but nothing coordinated at university level. | BB6: Yes | BC6: Yes | BD6: No | BE6: No | BF6: No | BG6: No | BH6: Our dept has informal practices but nothing coordinated at university level. | BI6: Yes | BJ6: Yes | BK6: No | BL6: No | BM6: No | BN6: No | BO6: No | BP6: No | BQ6: No | BR6: Our dept has informal practices but nothing coordinated at university level. | BS6: Yes | BT6: Yes | BU6: No | BV6: No | BW6: No | BX6: No | BY6: No | BZ6: No | CA6: Our dept has informal practices but nothing coordinated at university level. | CC6: Yes | CD6: Yes | CE6: Yes | CF6: No | CG6: No | CH6: No | CI6: No | CJ6: This would greatly help our research group's open source projects. | CK6: Yes | CL6: Yes | CM6: Yes | CN6: No | CO6: This would greatly help our research group's open source projects. | CP6: Yes | CQ6: Yes | CR6: Yes | CS6: No | CT6: No | CU6: This would greatly help our research group's open source projects. | CV6: Yes | CW6: Yes | CX6: Yes | CY6: No | CZ6: No | DA6: This would greatly help our research group's open source projects. | DB6: Yes | DC6: Yes | DD6: Yes | DE6: No | DF6: No | DG6: This would greatly help our research group's open source projects. | DH6: Yes | DI6: Yes | DJ6: Yes | DK6: No | DL6: No | DM6: No | DN6: No | DO6: No | DP6: No | DQ6: This would greatly help our research group's open source projects. | DR6: Yes | DS6: Yes | DT6: Yes | DU6: No | DV6: No | DW6: No | DX6: This would greatly help our research group's open source projects. | DZ6: Yes | EA6: Yes | EB6: Yes | EC6: No | ED6: No | EE6: No | EG6: Yes | EH6: Yes | EI6: No | EJ6: No | EK6: No | EL6: No | EM6: No | EN6: No | EO6: No | EP6: Yes | EQ6: Yes | ER6: No | ES6: No | ET6: No | EU6: No | EV6: No | EW6: No | EX6: No | EY6: No | FA6: Yes | FB6: Yes | FC6: No | FD6: No | FE6: No | FF6: No | FG6: No | FH6: No | FI6: No | FK6: Yes | FL6: Yes | FM6: No | FN6: No | FO6: No | FP6: No | FQ6: No | FS6: Yes | FT6: Yes | FU6: No | FV6: No | FW6: No | FX6: No | FY6: No | FZ6: No | GA6: No | GB6: No | GC6: No | GD6: No | GE6: No | GF6: No | GG6: No | GI6: Excellent initiative! Open source is central to reproducible research. Example University needs a formal OSPO.
A7: 6 | B7: 1980-01-01 00:00:00 | C7: 25 | D7: en | E7: 613434798 | F7: Leadership / Administration | G7: Office of Research Administration | H7: Not important | I7: N/A | J7: N/A | K7: N/A | L7: N/A | M7: N/A | N7: N/A | O7: N/A | P7: N/A | R7: Not confident | T7: N/A | U7: N/A | V7: N/A | W7: N/A | X7: Yes | Y7: I'm not sure we have any practices related to this. | Z7: N/A | AA7: N/A | AB7: N/A | AC7: N/A | AD7: N/A | AE7: N/A | AF7: Yes | AG7: I'm not sure we have any practices related to this. | AH7: N/A | AI7: N/A | AJ7: N/A | AK7: Yes | AL7: I'm not sure we have any practices related to this. | AM7: N/A | AN7: N/A | AO7: N/A | AP7: N/A | AQ7: N/A | AR7: N/A | AS7: Yes | AT7: I'm not sure we have any practices related to this. | AU7: N/A | AV7: N/A | AW7: N/A | AX7: N/A | AY7: N/A | AZ7: Yes | BA7: I'm not sure we have any practices related to this. | BB7: N/A | BC7: N/A | BD7: N/A | BE7: N/A | BF7: N/A | BG7: Yes | BH7: I'm not sure we have any practices related to this. | BI7: N/A | BJ7: N/A | BK7: N/A | BL7: N/A | BM7: N/A | BN7: N/A | BO7: N/A | BP7: N/A | BQ7: Yes | BR7: I'm not sure we have any practices related to this. | BS7: N/A | BT7: N/A | BU7: N/A | BV7: N/A | BW7: N/A | BX7: N/A | BY7: N/A | BZ7: Yes | CA7: I'm not sure we have any practices related to this. | CC7: N/A | CD7: N/A | CE7: N/A | CF7: N/A | CG7: N/A | CH7: N/A | CI7: Yes | CJ7: Not sure this is relevant to our office. | CK7: N/A | CL7: N/A | CM7: N/A | CN7: Yes | CO7: Not sure this is relevant to our office. | CP7: N/A | CQ7: N/A | CR7: N/A | CS7: N/A | CT7: Yes | CU7: Not sure this is relevant to our office. | CV7: N/A | CW7: N/A | CX7: N/A | CY7: N/A | CZ7: Yes | DA7: Not sure this is relevant to our office. | DB7: N/A | DC7: N/A | DD7: N/A | DE7: N/A | DF7: Yes | DG7: Not sure this is relevant to our office. | DH7: N/A | DI7: N/A | DJ7: N/A | DK7: N/A | DL7: N/A | DM7: N/A | DN7: N/A | DO7: N/A | DP7: Yes | DQ7: Not sure this is relevant to our office. | DR7: N/A | DS7: N/A | DT7: N/A | DU7: N/A | DV7: N/A | DW7: Yes | DX7: Not sure this is relevant to our office. | DZ7: No | EA7: N/A | EB7: N/A | EC7: N/A | ED7: N/A | EE7: N/A | EG7: N/A | EH7: N/A | EI7: N/A | EJ7: N/A | EK7: N/A | EL7: N/A | EM7: N/A | EN7: N/A | EO7: N/A | EP7: N/A | EQ7: N/A | ER7: N/A | ES7: N/A | ET7: N/A | EU7: N/A | EV7: N/A | EW7: N/A | EX7: N/A | EY7: N/A | FA7: N/A | FB7: N/A | FC7: N/A | FD7: N/A | FE7: N/A | FF7: N/A | FG7: N/A | FH7: N/A | FI7: N/A | FK7: N/A | FL7: N/A | FM7: N/A | FN7: N/A | FO7: N/A | FP7: N/A | FQ7: N/A | FS7: N/A | FT7: N/A | FU7: N/A | FV7: N/A | FW7: N/A | FX7: N/A | FY7: N/A | FZ7: N/A | GA7: N/A | GB7: N/A | GC7: N/A | GD7: N/A | GE7: N/A | GF7: N/A | GG7: N/A | GI7: I wasn't sure what this survey was about. The questions felt overly technical for administrative staff.
A8: 7 | B8: 1980-01-01 00:00:00 | C8: 25 | D8: en | E8: 2102043223 | F8: Professional / Support staff (including IT and library) | G8: University Libraries | H8: Important | I8: Yes | J8: Yes | K8: No | L8: No | M8: No | N8: No | O8: No | P8: No | R8: Somewhat confident | T8: Yes | U8: No | V8: No | W8: No | X8: No | Y8: We support open access publishing but don't have specific open source policies. | Z8: Yes | AA8: No | AB8: No | AC8: No | AD8: No | AE8: No | AF8: No | AG8: We support open access publishing but don't have specific open source policies. | AH8: Yes | AI8: No | AJ8: No | AK8: No | AL8: We support open access publishing but don't have specific open source policies. | AM8: Yes | AN8: No | AO8: No | AP8: No | AQ8: No | AR8: No | AS8: No | AT8: We support open access publishing but don't have specific open source policies. | AU8: Yes | AV8: No | AW8: No | AX8: No | AY8: No | AZ8: No | BA8: We support open access publishing but don't have specific open source policies. | BB8: Yes | BC8: No | BD8: No | BE8: No | BF8: No | BG8: No | BH8: We support open access publishing but don't have specific open source policies. | BI8: Yes | BJ8: No | BK8: No | BL8: No | BM8: No | BN8: No | BO8: No | BP8: No | BQ8: No | BR8: We support open access publishing but don't have specific open source policies. | BS8: Yes | BT8: No | BU8: No | BV8: No | BW8: No | BX8: No | BY8: No | BZ8: No | CA8: We support open access publishing but don't have specific open source policies. | CC8: Yes | CD8: Yes | CE8: No | CF8: No | CG8: No | CH8: No | CI8: No | CJ8: Libraries could play a neutral hosting role for OSPO services. | CK8: Yes | CL8: Yes | CM8: No | CN8: No | CO8: Libraries could play a neutral hosting role for OSPO services. | CP8: Yes | CQ8: Yes | CR8: No | CS8: No | CT8: No | CU8: Libraries could play a neutral hosting role for OSPO services. | CV8: Yes | CW8: Yes | CX8: No | CY8: No | CZ8: No | DA8: Libraries could play a neutral hosting role for OSPO services. | DB8: Yes | DC8: Yes | DD8: No | DE8: No | DF8: No | DG8: Libraries could play a neutral hosting role for OSPO services. | DH8: Yes | DI8: Yes | DJ8: No | DK8: No | DL8: No | DM8: No | DN8: No | DO8: No | DP8: No | DQ8: Libraries could play a neutral hosting role for OSPO services. | DR8: Yes | DS8: Yes | DT8: No | DU8: No | DV8: No | DW8: No | DX8: Libraries could play a neutral hosting role for OSPO services. | DZ8: Yes | EA8: Yes | EB8: No | EC8: No | ED8: No | EE8: No | EG8: Yes | EH8: No | EI8: No | EJ8: No | EK8: No | EL8: No | EM8: No | EN8: No | EO8: No | EP8: Yes | EQ8: No | ER8: No | ES8: No | ET8: No | EU8: No | EV8: No | EW8: No | EX8: No | EY8: No | FA8: Yes | FB8: No | FC8: No | FD8: No | FE8: No | FF8: No | FG8: No | FH8: No | FI8: No | FK8: Yes | FL8: No | FM8: No | FN8: No | FO8: No | FP8: No | FQ8: No | FS8: Yes | FT8: No | FU8: No | FV8: No | FW8: No | FX8: No | FY8: No | FZ8: No | GA8: No | GB8: No | GC8: No | GD8: No | GE8: No | GF8: No | GG8: No | GI8: Interesting survey. Some questions were technical but the overall flow was clear.
A9: 8 | B9: 1980-01-01 00:00:00 | C9: 25 | D9: en | E9: 298488991 | F9: Student (graduate or undergraduate) | G9: Department of Biological Sciences | H9: Critical | I9: No | J9: No | K9: Yes | L9: Yes | M9: No | N9: Yes | O9: No | P9: No | R9: Somewhat confident | T9: No | U9: No | V9: Yes | W9: No | X9: No | Y9: Not aware of any formal support — our lab uses R and Python informally, guided by the PI. | Z9: N/A | AA9: N/A | AB9: N/A | AC9: N/A | AD9: N/A | AE9: N/A | AF9: Yes | AG9: I'm not aware of any compliance support for grad students working with open source code. | AH9: N/A | AI9: N/A | AJ9: N/A | AK9: Yes | AL9: IT department maybe, but I don't have visibility into this as a grad student. | AM9: No | AN9: Yes | AO9: No | AP9: Yes | AQ9: No | AR9: No | AS9: No | AT9: Our department encourages R and Python. I've never faced barriers installing open source tools. | AU9: N/A | AV9: N/A | AW9: N/A | AX9: N/A | AY9: N/A | AZ9: Yes | BA9: Nothing formal. My advisor approves what I post on GitHub but there's no university-level policy I'm aware of. | BB9: N/A | BC9: N/A | BD9: N/A | BE9: N/A | BF9: N/A | BG9: Yes | BH9: I'm not aware of any outreach or recognition for open source contributions from grad students. | BI9: No | BJ9: No | BK9: No | BL9: No | BM9: No | BN9: No | BO9: No | BP9: Yes | BQ9: No | BR9: The university HPC cluster is available for research computing. Not sure if it counts as open source support specifically. | BS9: Yes | BT9: No | BU9: No | BV9: Yes | BW9: No | BX9: No | BY9: No | BZ9: No | CA9: My PI and department chair seem supportive of open science, but I don't know of any formal budget or strategy for it. | CC9: Yes | CD9: No | CE9: No | CF9: No | CG9: Yes | CH9: No | CI9: No | CJ9: I'd love help understanding which license to use when releasing my analysis code. My PI isn't sure either. | CK9: Yes | CL9: No | CM9: Yes | CN9: No | CO9: A curated catalogue of recommended bioinformatics and data analysis tools would be extremely helpful for our lab. | CP9: No | CQ9: Yes | CR9: Yes | CS9: No | CT9: No | CU9: Our lab has built several analysis pipelines. I'd love support on how to properly open-source and document them for the community. | CV9: Yes | CW9: Yes | CX9: No | CY9: Yes | CZ9: No | DA9: Workshops on research software best practices and open source would be great. A community of grad students working on open science tools would also be valuable. | DB9: Yes | DC9: No | DD9: Yes | DE9: No | DF9: No | DG9: Knowing about funding opportunities specifically for open source research software would be very useful, especially for dissertation-related code. | DH9: No | DI9: No | DJ9: Yes | DK9: Yes | DL9: Yes | DM9: No | DN9: No | DO9: No | DP9: No | DQ9: Genomics data is enormous — affordable cloud storage and compute access would remove a major bottleneck for sharing reproducible analyses. | DR9: No | DS9: No | DT9: Yes | DU9: No | DV9: Yes | DW9: No | DX9: Open science hackathons would help build community. Help measuring the impact of our research software would also strengthen grant applications. | DZ9: Yes | EA9: No | EB9: Yes | EC9: Yes | ED9: Yes | EE9: No | EF9: Mostly use R and Python packages for bioinformatics; occasionally submit bug reports or small patches. | EG9: Yes | EH9: No | EI9: No | EJ9: Yes | EK9: Yes | EL9: No | EM9: No | EN9: No | EO9: No | EP9: No | EQ9: Yes | ER9: Yes | ES9: No | ET9: No | EU9: No | EV9: No | EW9: No | EX9: No | EY9: No | EZ9: Primarily a user who occasionally contributes fixes to R packages I rely on for my dissertation research. | FA9: No | FB9: No | FC9: Yes | FD9: Yes | FE9: No | FF9: Yes | FG9: Yes | FH9: No | FI9: No | FK9: No | FL9: No | FM9: No | FN9: Yes | FO9: Yes | FP9: No | FQ9: No | FR9: R packages and Python scripts for bioinformatics and statistical analysis. | FS9: Yes | FT9: Yes | FU9: No | FV9: No | FW9: Yes | FX9: No | FY9: No | FZ9: No | GA9: No | GB9: No | GC9: No | GD9: Yes | GE9: Yes | GF9: No | GG9: No | GI9: Really glad someone is asking these questions. As a grad student, open source is essential to my reproducibility work but I feel unsupported — no guidance on licensing, no funding, and no recognition. An OSPO that serves early-career researchers specifically would be transformative. Survey took about 12 minutes, felt thorough.
A10: 9 | B10: 1980-01-01 00:00:00 | C10: 25 | D10: en | E10: 101380080 | F10: Faculty / Academic staff | H10: Somewhat important | I10: Yes | J10: No | K10: No | L10: No | M10: Yes | N10: No | O10: No | P10: No | R10: Somewhat confident | T10: N/A | U10: N/A | V10: N/A | W10: N/A | X10: Yes | Z10: N/A | AA10: N/A | AB10: N/A | AC10: N/A | AD10: N/A | AE10: N/A | AF10: Yes | AH10: Yes | AI10: No | AJ10: No | AK10: No | AM10: Yes | AN10: No | AO10: Yes | AP10: No | AQ10: No | AR10: No | AS10: No | AU10: No | AV10: Yes | AW10: No | AX10: No | AY10: No | AZ10: No | BB10: N/A | BC10: N/A | BD10: N/A | BE10: N/A | BF10: N/A | BG10: Yes | BI10: Yes | BJ10: No | BK10: No | BL10: No | BM10: No | BN10: No | BO10: No | BP10: No | BQ10: No | BS10: Yes | BT10: No | BU10: No | BV10: No | BW10: No | BX10: No | BY10: No | BZ10: No | CC10: No | CD10: Yes | CE10: Yes | CF10: No | CG10: No | CH10: No | CI10: No | CK10: Yes | CL10: No | CM10: No | CN10: No | CP10: Yes | CQ10: No | CR10: Yes | CS10: No | CT10: No | CV10: N/A | CW10: N/A | CX10: N/A | CY10: N/A | CZ10: Yes | DB10: Yes | DC10: No | DD10: No | DE10: No | DF10: No | DH10: No | DI10: No | DJ10: No | DK10: No | DL10: Yes | DM10: Yes | DN10: No | DO10: No | DP10: No | DR10: No | DS10: No | DT10: Yes | DU10: No | DV10: No | DW10: No | DZ10: Yes | EA10: No | EB10: Yes | EC10: Yes | ED10: No | EE10: No | EG10: Yes | EH10: No | EI10: Yes | EJ10: No | EK10: No | EL10: No | EM10: No | EN10: No | EO10: No | EP10: No | EQ10: Yes | ER10: No | ES10: No | ET10: No | EU10: No | EV10: No | EW10: No | EX10: No | EY10: No | FA10: No | FB10: No | FC10: Yes | FD10: Yes | FE10: No | FF10: No | FG10: No | FH10: No | FI10: No | FK10: No | FL10: No | FM10: Yes | FN10: Yes | FO10: No | FP10: No | FQ10: No | FS10: Yes | FT10: No | FU10: No | FV10: No | FW10: Yes | FX10: No | FY10: No | FZ10: No | GA10: No | GB10: No | GC10: No | GD10: No | GE10: No | GF10: No | GG10: No | GI10: Survey was clear but felt lengthy. The 8 practices sections are repetitive — could perhaps be condensed. Took about 13 minutes. The distinction between "practices" and "support needs" was not always obvious.
A11: 10 | B11: 1980-01-01 00:00:00 | C11: 25 | D11: en | E11: 2080563162 | F11: Leadership / Administration | H11: Important | I11: Yes | J11: Yes | K11: No | L11: No | M11: No | N11: No | O11: Yes | P11: No | R11: Confident | T11: No | U11: Yes | V11: Yes | W11: No | X11: No | Z11: Yes | AA11: Yes | AB11: No | AC11: Yes | AD11: No | AE11: No | AF11: No | AH11: Yes | AI11: Yes | AJ11: Yes | AK11: No | AM11: Yes | AN11: No | AO11: Yes | AP11: Yes | AQ11: No | AR11: No | AS11: No | AU11: N/A | AV11: N/A | AW11: N/A | AX11: N/A | AY11: N/A | AZ11: Yes | BB11: N/A | BC11: N/A | BD11: N/A | BE11: N/A | BF11: N/A | BG11: Yes | BI11: Yes | BJ11: Yes | BK11: No | BL11: No | BM11: No | BN11: No | BO11: No | BP11: No | BQ11: No | BS11: Yes | BT11: Yes | BU11: No | BV11: No | BW11: No | BX11: No | BY11: No | BZ11: No | CC11: No | CD11: Yes | CE11: Yes | CF11: No | CG11: Yes | CH11: No | CI11: No | CK11: Yes | CL11: Yes | CM11: No | CN11: No | CP11: Yes | CQ11: No | CR11: Yes | CS11: No | CT11: No | CV11: N/A | CW11: N/A | CX11: N/A | CY11: N/A | CZ11: Yes | DB11: N/A | DC11: N/A | DD11: N/A | DE11: N/A | DF11: Yes | DH11: No | DI11: No | DJ11: No | DK11: Yes | DL11: Yes | DM11: Yes | DN11: No | DO11: No | DP11: No | DR11: Yes | DS11: No | DT11: Yes | DU11: No | DV11: No | DW11: No | DZ11: No | EA11: N/A | EB11: N/A | EC11: N/A | ED11: N/A | EE11: N/A | EG11: N/A | EH11: N/A | EI11: N/A | EJ11: N/A | EK11: N/A | EL11: N/A | EM11: N/A | EN11: N/A | EO11: N/A | EP11: N/A | EQ11: N/A | ER11: N/A | ES11: N/A | ET11: N/A | EU11: N/A | EV11: N/A | EW11: N/A | EX11: N/A | EY11: N/A | FA11: N/A | FB11: N/A | FC11: N/A | FD11: N/A | FE11: N/A | FF11: N/A | FG11: N/A | FH11: N/A | FI11: N/A | FK11: N/A | FL11: N/A | FM11: N/A | FN11: N/A | FO11: N/A | FP11: N/A | FQ11: N/A | FS11: N/A | FT11: N/A | FU11: N/A | FV11: N/A | FW11: N/A | FX11: N/A | FY11: N/A | FZ11: N/A | GA11: N/A | GB11: N/A | GC11: N/A | GD11: N/A | GE11: N/A | GF11: N/A | GG11: N/A | GI11: Well-designed survey. Security and compliance aspects are most critical for IT. The practices/support split made sense from an IT governance perspective. Took about 11 minutes.
A12: 11 | C12: 2 | D12: en | E12: 1113535850 | F12: Faculty / Academic staff | H12: Not important | I12: N/A | J12: N/A | K12: N/A | L12: N/A | M12: N/A | N12: N/A | O12: N/A | P12: N/A | T12: N/A | U12: N/A | V12: N/A | W12: N/A | X12: N/A | Z12: N/A | AA12: N/A | AB12: N/A | AC12: N/A | AD12: N/A | AE12: N/A | AF12: N/A | AH12: N/A | AI12: N/A | AJ12: N/A | AK12: N/A | AM12: N/A | AN12: N/A | AO12: N/A | AP12: N/A | AQ12: N/A | AR12: N/A | AS12: N/A | AU12: N/A | AV12: N/A | AW12: N/A | AX12: N/A | AY12: N/A | AZ12: N/A | BB12: N/A | BC12: N/A | BD12: N/A | BE12: N/A | BF12: N/A | BG12: N/A | BI12: N/A | BJ12: N/A | BK12: N/A | BL12: N/A | BM12: N/A | BN12: N/A | BO12: N/A | BP12: N/A | BQ12: N/A | BS12: N/A | BT12: N/A | BU12: N/A | BV12: N/A | BW12: N/A | BX12: N/A | BY12: N/A | BZ12: N/A | CC12: N/A | CD12: N/A | CE12: N/A | CF12: N/A | CG12: N/A | CH12: N/A | CI12: N/A | CK12: N/A | CL12: N/A | CM12: N/A | CN12: N/A | CP12: N/A | CQ12: N/A | CR12: N/A | CS12: N/A | CT12: N/A | CV12: N/A | CW12: N/A | CX12: N/A | CY12: N/A | CZ12: N/A | DB12: N/A | DC12: N/A | DD12: N/A | DE12: N/A | DF12: N/A | DH12: N/A | DI12: N/A | DJ12: N/A | DK12: N/A | DL12: N/A | DM12: N/A | DN12: N/A | DO12: N/A | DP12: N/A | DR12: N/A | DS12: N/A | DT12: N/A | DU12: N/A | DV12: N/A | DW12: N/A | DZ12: N/A | EA12: N/A | EB12: N/A | EC12: N/A | ED12: N/A | EE12: N/A | EG12: N/A | EH12: N/A | EI12: N/A | EJ12: N/A | EK12: N/A | EL12: N/A | EM12: N/A | EN12: N/A | EO12: N/A | EP12: N/A | EQ12: N/A | ER12: N/A | ES12: N/A | ET12: N/A | EU12: N/A | EV12: N/A | EW12: N/A | EX12: N/A | EY12: N/A | FA12: N/A | FB12: N/A | FC12: N/A | FD12: N/A | FE12: N/A | FF12: N/A | FG12: N/A | FH12: N/A | FI12: N/A | FK12: N/A | FL12: N/A | FM12: N/A | FN12: N/A | FO12: N/A | FP12: N/A | FQ12: N/A | FS12: N/A | FT12: N/A | FU12: N/A | FV12: N/A | FW12: N/A | FX12: N/A | FY12: N/A | FZ12: N/A | GA12: N/A | GB12: N/A | GC12: N/A | GD12: N/A | GE12: N/A | GF12: N/A | GG12: N/A
A13: 12 | C13: 2 | D13: en | E13: 846659208 | F13: Student (graduate or undergraduate) | H13: Important | I13: No | J13: No | K13: Yes | L13: No | M13: No | N13: Yes | O13: No | P13: No | T13: N/A | U13: N/A | V13: N/A | W13: N/A | X13: N/A | Z13: N/A | AA13: N/A | AB13: N/A | AC13: N/A | AD13: N/A | AE13: N/A | AF13: N/A | AH13: N/A | AI13: N/A | AJ13: N/A | AK13: N/A | AM13: N/A | AN13: N/A | AO13: N/A | AP13: N/A | AQ13: N/A | AR13: N/A | AS13: N/A | AU13: N/A | AV13: N/A | AW13: N/A | AX13: N/A | AY13: N/A | AZ13: N/A | BB13: N/A | BC13: N/A | BD13: N/A | BE13: N/A | BF13: N/A | BG13: N/A | BI13: N/A | BJ13: N/A | BK13: N/A | BL13: N/A | BM13: N/A | BN13: N/A | BO13: N/A | BP13: N/A | BQ13: N/A | BS13: N/A | BT13: N/A | BU13: N/A | BV13: N/A | BW13: N/A | BX13: N/A | BY13: N/A | BZ13: N/A | CC13: N/A | CD13: N/A | CE13: N/A | CF13: N/A | CG13: N/A | CH13: N/A | CI13: N/A | CK13: N/A | CL13: N/A | CM13: N/A | CN13: N/A | CP13: N/A | CQ13: N/A | CR13: N/A | CS13: N/A | CT13: N/A | CV13: N/A | CW13: N/A | CX13: N/A | CY13: N/A | CZ13: N/A | DB13: N/A | DC13: N/A | DD13: N/A | DE13: N/A | DF13: N/A | DH13: N/A | DI13: N/A | DJ13: N/A | DK13: N/A | DL13: N/A | DM13: N/A | DN13: N/A | DO13: N/A | DP13: N/A | DR13: N/A | DS13: N/A | DT13: N/A | DU13: N/A | DV13: N/A | DW13: N/A | DZ13: N/A | EA13: N/A | EB13: N/A | EC13: N/A | ED13: N/A | EE13: N/A | EG13: N/A | EH13: N/A | EI13: N/A | EJ13: N/A | EK13: N/A | EL13: N/A | EM13: N/A | EN13: N/A | EO13: N/A | EP13: N/A | EQ13: N/A | ER13: N/A | ES13: N/A | ET13: N/A | EU13: N/A | EV13: N/A | EW13: N/A | EX13: N/A | EY13: N/A | FA13: N/A | FB13: N/A | FC13: N/A | FD13: N/A | FE13: N/A | FF13: N/A | FG13: N/A | FH13: N/A | FI13: N/A | FK13: N/A | FL13: N/A | FM13: N/A | FN13: N/A | FO13: N/A | FP13: N/A | FQ13: N/A | FS13: N/A | FT13: N/A | FU13: N/A | FV13: N/A | FW13: N/A | FX13: N/A | FY13: N/A | FZ13: N/A | GA13: N/A | GB13: N/A | GC13: N/A | GD13: N/A | GE13: N/A | GF13: N/A | GG13: N/A
A14: 13 | C14: 2 | D14: en | E14: 559955886 | F14: Leadership / Administration | H14: Somewhat important | I14: No | J14: Yes | K14: No | L14: No | M14: No | N14: No | O14: No | P14: No | T14: N/A | U14: N/A | V14: N/A | W14: N/A | X14: N/A | Z14: N/A | AA14: N/A | AB14: N/A | AC14: N/A | AD14: N/A | AE14: N/A | AF14: N/A | AH14: N/A | AI14: N/A | AJ14: N/A | AK14: N/A | AM14: N/A | AN14: N/A | AO14: N/A | AP14: N/A | AQ14: N/A | AR14: N/A | AS14: N/A | AU14: N/A | AV14: N/A | AW14: N/A | AX14: N/A | AY14: N/A | AZ14: N/A | BB14: N/A | BC14: N/A | BD14: N/A | BE14: N/A | BF14: N/A | BG14: N/A | BI14: N/A | BJ14: N/A | BK14: N/A | BL14: N/A | BM14: N/A | BN14: N/A | BO14: N/A | BP14: N/A | BQ14: N/A | BS14: N/A | BT14: N/A | BU14: N/A | BV14: N/A | BW14: N/A | BX14: N/A | BY14: N/A | BZ14: N/A | CC14: N/A | CD14: N/A | CE14: N/A | CF14: N/A | CG14: N/A | CH14: N/A | CI14: N/A | CK14: N/A | CL14: N/A | CM14: N/A | CN14: N/A | CP14: N/A | CQ14: N/A | CR14: N/A | CS14: N/A | CT14: N/A | CV14: N/A | CW14: N/A | CX14: N/A | CY14: N/A | CZ14: N/A | DB14: N/A | DC14: N/A | DD14: N/A | DE14: N/A | DF14: N/A | DH14: N/A | DI14: N/A | DJ14: N/A | DK14: N/A | DL14: N/A | DM14: N/A | DN14: N/A | DO14: N/A | DP14: N/A | DR14: N/A | DS14: N/A | DT14: N/A | DU14: N/A | DV14: N/A | DW14: N/A | DZ14: N/A | EA14: N/A | EB14: N/A | EC14: N/A | ED14: N/A | EE14: N/A | EG14: N/A | EH14: N/A | EI14: N/A | EJ14: N/A | EK14: N/A | EL14: N/A | EM14: N/A | EN14: N/A | EO14: N/A | EP14: N/A | EQ14: N/A | ER14: N/A | ES14: N/A | ET14: N/A | EU14: N/A | EV14: N/A | EW14: N/A | EX14: N/A | EY14: N/A | FA14: N/A | FB14: N/A | FC14: N/A | FD14: N/A | FE14: N/A | FF14: N/A | FG14: N/A | FH14: N/A | FI14: N/A | FK14: N/A | FL14: N/A | FM14: N/A | FN14: N/A | FO14: N/A | FP14: N/A | FQ14: N/A | FS14: N/A | FT14: N/A | FU14: N/A | FV14: N/A | FW14: N/A | FX14: N/A | FY14: N/A | FZ14: N/A | GA14: N/A | GB14: N/A | GC14: N/A | GD14: N/A | GE14: N/A | GF14: N/A | GG14: N/A
A15: 14 | C15: 12 | D15: en | E15: 1887887645 | F15: Professional / Support staff (including IT and library) | H15: Somewhat important | I15: No | J15: No | K15: No | L15: Yes | M15: No | N15: No | O15: No | P15: No | R15: Not confident | T15: N/A | U15: N/A | V15: N/A | W15: N/A | X15: Yes | Z15: N/A | AA15: N/A | AB15: N/A | AC15: N/A | AD15: N/A | AE15: N/A | AF15: Yes | AH15: N/A | AI15: N/A | AJ15: N/A | AK15: Yes | AM15: N/A | AN15: N/A | AO15: N/A | AP15: N/A | AQ15: N/A | AR15: N/A | AS15: Yes | AU15: N/A | AV15: N/A | AW15: N/A | AX15: N/A | AY15: N/A | AZ15: Yes | BB15: N/A | BC15: N/A | BD15: N/A | BE15: N/A | BF15: N/A | BG15: Yes | BI15: N/A | BJ15: N/A | BK15: N/A | BL15: N/A | BM15: N/A | BN15: N/A | BO15: N/A | BP15: N/A | BQ15: Yes | BS15: N/A | BT15: N/A | BU15: N/A | BV15: N/A | BW15: N/A | BX15: N/A | BY15: N/A | BZ15: Yes | CC15: N/A | CD15: N/A | CE15: N/A | CF15: N/A | CG15: N/A | CH15: N/A | CI15: N/A | CK15: N/A | CL15: N/A | CM15: N/A | CN15: N/A | CP15: N/A | CQ15: N/A | CR15: N/A | CS15: N/A | CT15: N/A | CV15: N/A | CW15: N/A | CX15: N/A | CY15: N/A | CZ15: N/A | DB15: N/A | DC15: N/A | DD15: N/A | DE15: N/A | DF15: N/A | DH15: N/A | DI15: N/A | DJ15: N/A | DK15: N/A | DL15: N/A | DM15: N/A | DN15: N/A | DO15: N/A | DP15: N/A | DR15: N/A | DS15: N/A | DT15: N/A | DU15: N/A | DV15: N/A | DW15: N/A | DZ15: N/A | EA15: N/A | EB15: N/A | EC15: N/A | ED15: N/A | EE15: N/A | EG15: N/A | EH15: N/A | EI15: N/A | EJ15: N/A | EK15: N/A | EL15: N/A | EM15: N/A | EN15: N/A | EO15: N/A | EP15: N/A | EQ15: N/A | ER15: N/A | ES15: N/A | ET15: N/A | EU15: N/A | EV15: N/A | EW15: N/A | EX15: N/A | EY15: N/A | FA15: N/A | FB15: N/A | FC15: N/A | FD15: N/A | FE15: N/A | FF15: N/A | FG15: N/A | FH15: N/A | FI15: N/A | FK15: N/A | FL15: N/A | FM15: N/A | FN15: N/A | FO15: N/A | FP15: N/A | FQ15: N/A | FS15: N/A | FT15: N/A | FU15: N/A | FV15: N/A | FW15: N/A | FX15: N/A | FY15: N/A | FZ15: N/A | GA15: N/A | GB15: N/A | GC15: N/A | GD15: N/A | GE15: N/A | GF15: N/A | GG15: N/A
A16: 15 | C16: 12 | D16: en | E16: 929693758 | F16: Professional / Support staff (including IT and library) | H16: Important | I16: No | J16: No | K16: Yes | L16: No | M16: No | N16: No | O16: No | P16: No | R16: Somewhat confident | T16: N/A | U16: N/A | V16: N/A | W16: N/A | X16: Yes | Z16: N/A | AA16: N/A | AB16: N/A | AC16: N/A | AD16: N/A | AE16: N/A | AF16: Yes | AH16: N/A | AI16: N/A | AJ16: N/A | AK16: Yes | AM16: N/A | AN16: N/A | AO16: N/A | AP16: N/A | AQ16: N/A | AR16: N/A | AS16: Yes | AU16: N/A | AV16: N/A | AW16: N/A | AX16: N/A | AY16: N/A | AZ16: Yes | BB16: N/A | BC16: N/A | BD16: N/A | BE16: N/A | BF16: N/A | BG16: Yes | BI16: N/A | BJ16: N/A | BK16: N/A | BL16: N/A | BM16: N/A | BN16: N/A | BO16: N/A | BP16: N/A | BQ16: Yes | BS16: N/A | BT16: N/A | BU16: N/A | BV16: N/A | BW16: N/A | BX16: N/A | BY16: N/A | BZ16: Yes | CC16: N/A | CD16: N/A | CE16: N/A | CF16: N/A | CG16: N/A | CH16: N/A | CI16: N/A | CK16: N/A | CL16: N/A | CM16: N/A | CN16: N/A | CP16: N/A | CQ16: N/A | CR16: N/A | CS16: N/A | CT16: N/A | CV16: N/A | CW16: N/A | CX16: N/A | CY16: N/A | CZ16: N/A | DB16: N/A | DC16: N/A | DD16: N/A | DE16: N/A | DF16: N/A | DH16: N/A | DI16: N/A | DJ16: N/A | DK16: N/A | DL16: N/A | DM16: N/A | DN16: N/A | DO16: N/A | DP16: N/A | DR16: N/A | DS16: N/A | DT16: N/A | DU16: N/A | DV16: N/A | DW16: N/A | DZ16: N/A | EA16: N/A | EB16: N/A | EC16: N/A | ED16: N/A | EE16: N/A | EG16: N/A | EH16: N/A | EI16: N/A | EJ16: N/A | EK16: N/A | EL16: N/A | EM16: N/A | EN16: N/A | EO16: N/A | EP16: N/A | EQ16: N/A | ER16: N/A | ES16: N/A | ET16: N/A | EU16: N/A | EV16: N/A | EW16: N/A | EX16: N/A | EY16: N/A | FA16: N/A | FB16: N/A | FC16: N/A | FD16: N/A | FE16: N/A | FF16: N/A | FG16: N/A | FH16: N/A | FI16: N/A | FK16: N/A | FL16: N/A | FM16: N/A | FN16: N/A | FO16: N/A | FP16: N/A | FQ16: N/A | FS16: N/A | FT16: N/A | FU16: N/A | FV16: N/A | FW16: N/A | FX16: N/A | FY16: N/A | FZ16: N/A | GA16: N/A | GB16: N/A | GC16: N/A | GD16: N/A | GE16: N/A | GF16: N/A | GG16: N/A
A17: 16 | C17: 12 | D17: en | E17: 1398180987 | F17: Faculty / Academic staff | G17: Arts & Humanities | H17: Somewhat important | I17: No | J17: Yes | K17: Yes | L17: No | M17: No | N17: No | O17: No | P17: No | R17: Not confident | T17: N/A | U17: N/A | V17: N/A | W17: N/A | X17: Yes | Z17: N/A | AA17: N/A | AB17: N/A | AC17: N/A | AD17: N/A | AE17: N/A | AF17: Yes | AH17: N/A | AI17: N/A | AJ17: N/A | AK17: Yes | AM17: N/A | AN17: N/A | AO17: N/A | AP17: N/A | AQ17: N/A | AR17: N/A | AS17: Yes | AU17: N/A | AV17: N/A | AW17: N/A | AX17: N/A | AY17: N/A | AZ17: Yes | BB17: N/A | BC17: N/A | BD17: N/A | BE17: N/A | BF17: N/A | BG17: Yes | BI17: N/A | BJ17: N/A | BK17: N/A | BL17: N/A | BM17: N/A | BN17: N/A | BO17: N/A | BP17: N/A | BQ17: Yes | BS17: N/A | BT17: N/A | BU17: N/A | BV17: N/A | BW17: N/A | BX17: N/A | BY17: N/A | BZ17: Yes | CC17: N/A | CD17: N/A | CE17: N/A | CF17: N/A | CG17: N/A | CH17: N/A | CI17: N/A | CK17: N/A | CL17: N/A | CM17: N/A | CN17: N/A | CP17: N/A | CQ17: N/A | CR17: N/A | CS17: N/A | CT17: N/A | CV17: N/A | CW17: N/A | CX17: N/A | CY17: N/A | CZ17: N/A | DB17: N/A | DC17: N/A | DD17: N/A | DE17: N/A | DF17: N/A | DH17: N/A | DI17: N/A | DJ17: N/A | DK17: N/A | DL17: N/A | DM17: N/A | DN17: N/A | DO17: N/A | DP17: N/A | DR17: N/A | DS17: N/A | DT17: N/A | DU17: N/A | DV17: N/A | DW17: N/A | DZ17: N/A | EA17: N/A | EB17: N/A | EC17: N/A | ED17: N/A | EE17: N/A | EG17: N/A | EH17: N/A | EI17: N/A | EJ17: N/A | EK17: N/A | EL17: N/A | EM17: N/A | EN17: N/A | EO17: N/A | EP17: N/A | EQ17: N/A | ER17: N/A | ES17: N/A | ET17: N/A | EU17: N/A | EV17: N/A | EW17: N/A | EX17: N/A | EY17: N/A | FA17: N/A | FB17: N/A | FC17: N/A | FD17: N/A | FE17: N/A | FF17: N/A | FG17: N/A | FH17: N/A | FI17: N/A | FK17: N/A | FL17: N/A | FM17: N/A | FN17: N/A | FO17: N/A | FP17: N/A | FQ17: N/A | FS17: N/A | FT17: N/A | FU17: N/A | FV17: N/A | FW17: N/A | FX17: N/A | FY17: N/A | FZ17: N/A | GA17: N/A | GB17: N/A | GC17: N/A | GD17: N/A | GE17: N/A | GF17: N/A | GG17: N/A
A18: 17 | B18: 1980-01-01 00:00:00 | C18: 25 | D18: en | E18: 716547709 | F18: Research staff (postdocs, research software engineers) | G18: Research Computing | H18: Critical | I18: N/A | J18: N/A | K18: N/A | L18: N/A | M18: N/A | N18: N/A | O18: N/A | P18: Yes | R18: Very confident | T18: N/A | U18: N/A | V18: N/A | W18: N/A | X18: Yes | Z18: N/A | AA18: N/A | AB18: N/A | AC18: N/A | AD18: N/A | AE18: N/A | AF18: Yes | AH18: N/A | AI18: N/A | AJ18: N/A | AK18: Yes | AM18: N/A | AN18: N/A | AO18: N/A | AP18: N/A | AQ18: N/A | AR18: N/A | AS18: Yes | AU18: N/A | AV18: N/A | AW18: N/A | AX18: N/A | AY18: N/A | AZ18: Yes | BB18: N/A | BC18: N/A | BD18: N/A | BE18: N/A | BF18: N/A | BG18: Yes | BI18: N/A | BJ18: N/A | BK18: N/A | BL18: N/A | BM18: N/A | BN18: N/A | BO18: N/A | BP18: N/A | BQ18: Yes | BS18: N/A | BT18: N/A | BU18: N/A | BV18: N/A | BW18: N/A | BX18: N/A | BY18: N/A | BZ18: Yes | CC18: N/A | CD18: N/A | CE18: N/A | CF18: N/A | CG18: N/A | CH18: N/A | CI18: Yes | CK18: N/A | CL18: N/A | CM18: N/A | CN18: Yes | CP18: N/A | CQ18: N/A | CR18: N/A | CS18: N/A | CT18: Yes | CV18: N/A | CW18: N/A | CX18: N/A | CY18: N/A | CZ18: Yes | DB18: N/A | DC18: N/A | DD18: N/A | DE18: N/A | DF18: Yes | DH18: N/A | DI18: N/A | DJ18: N/A | DK18: N/A | DL18: N/A | DM18: N/A | DN18: N/A | DO18: N/A | DP18: Yes | DR18: N/A | DS18: N/A | DT18: N/A | DU18: N/A | DV18: N/A | DW18: Yes | DZ18: Yes | EA18: N/A | EB18: N/A | EC18: N/A | ED18: N/A | EE18: Yes | EG18: N/A | EH18: N/A | EI18: N/A | EJ18: N/A | EK18: N/A | EL18: N/A | EM18: N/A | EN18: N/A | EO18: Yes | EP18: N/A | EQ18: N/A | ER18: N/A | ES18: N/A | ET18: N/A | EU18: N/A | EV18: N/A | EW18: N/A | EX18: N/A | EY18: Yes | FA18: N/A | FB18: N/A | FC18: N/A | FD18: N/A | FE18: N/A | FF18: N/A | FG18: N/A | FH18: N/A | FI18: Yes | FK18: N/A | FL18: N/A | FM18: N/A | FN18: N/A | FO18: N/A | FP18: N/A | FQ18: Yes | FS18: N/A | FT18: N/A | FU18: N/A | FV18: N/A | FW18: N/A | FX18: N/A | FY18: N/A | FZ18: N/A | GA18: N/A | GB18: N/A | GC18: N/A | GD18: N/A | GE18: N/A | GF18: N/A | GG18: Yes | GH18: Research software tools and libraries | GI18: Survey covers all key areas well.
A19: 18 | B19: 1980-01-01 00:00:00 | C19: 25 | D19: en | E19: 196341784 | F19: Professional / Support staff (including IT and library) | G19: Library Services | H19: Important | I19: N/A | J19: N/A | K19: N/A | L19: N/A | M19: N/A | N19: N/A | O19: N/A | P19: Yes | R19: Somewhat confident | T19: N/A | U19: N/A | V19: N/A | W19: N/A | X19: Yes | Z19: N/A | AA19: N/A | AB19: N/A | AC19: N/A | AD19: N/A | AE19: N/A | AF19: Yes | AH19: N/A | AI19: N/A | AJ19: N/A | AK19: Yes | AM19: N/A | AN19: N/A | AO19: N/A | AP19: N/A | AQ19: N/A | AR19: N/A | AS19: Yes | AU19: N/A | AV19: N/A | AW19: N/A | AX19: N/A | AY19: N/A | AZ19: Yes | BB19: N/A | BC19: N/A | BD19: N/A | BE19: N/A | BF19: N/A | BG19: Yes | BI19: N/A | BJ19: N/A | BK19: N/A | BL19: N/A | BM19: N/A | BN19: N/A | BO19: N/A | BP19: N/A | BQ19: Yes | BS19: N/A | BT19: N/A | BU19: N/A | BV19: N/A | BW19: N/A | BX19: N/A | BY19: N/A | BZ19: Yes | CC19: N/A | CD19: N/A | CE19: N/A | CF19: N/A | CG19: N/A | CH19: N/A | CI19: Yes | CK19: N/A | CL19: N/A | CM19: N/A | CN19: Yes | CP19: N/A | CQ19: N/A | CR19: N/A | CS19: N/A | CT19: Yes | CV19: N/A | CW19: N/A | CX19: N/A | CY19: N/A | CZ19: Yes | DB19: N/A | DC19: N/A | DD19: N/A | DE19: N/A | DF19: Yes | DH19: N/A | DI19: N/A | DJ19: N/A | DK19: N/A | DL19: N/A | DM19: N/A | DN19: N/A | DO19: N/A | DP19: Yes | DR19: N/A | DS19: N/A | DT19: N/A | DU19: N/A | DV19: N/A | DW19: Yes | DZ19: No | EA19: N/A | EB19: N/A | EC19: N/A | ED19: N/A | EE19: N/A | EG19: N/A | EH19: N/A | EI19: N/A | EJ19: N/A | EK19: N/A | EL19: N/A | EM19: N/A | EN19: N/A | EO19: N/A | EP19: N/A | EQ19: N/A | ER19: N/A | ES19: N/A | ET19: N/A | EU19: N/A | EV19: N/A | EW19: N/A | EX19: N/A | EY19: N/A | FA19: N/A | FB19: N/A | FC19: N/A | FD19: N/A | FE19: N/A | FF19: N/A | FG19: N/A | FH19: N/A | FI19: N/A | FK19: N/A | FL19: N/A | FM19: N/A | FN19: N/A | FO19: N/A | FP19: N/A | FQ19: N/A | FS19: N/A | FT19: N/A | FU19: N/A | FV19: N/A | FW19: N/A | FX19: N/A | FY19: N/A | FZ19: N/A | GA19: N/A | GB19: N/A | GC19: N/A | GD19: N/A | GE19: N/A | GF19: N/A | GG19: N/A | GI19: As library support staff I have very limited direct exposure to open source beyond using library systems. The survey felt quite technical for my role.
A20: 19 | B20: 1980-01-01 00:00:00 | C20: 25 | D20: en | E20: 1611517903 | F20: Leadership / Administration | H20: Important | I20: Yes | J20: No | K20: Yes | L20: Yes | M20: No | N20: Yes | O20: No | P20: No | R20: Confident | T20: No | U20: Yes | V20: Yes | W20: No | X20: No | Y20: Our Research Services office handles policy guidance on an ad hoc basis, drawing on input from IT and the Office of Research Compliance. | Z20: No | AA20: No | AB20: Yes | AC20: Yes | AD20: No | AE20: No | AF20: No | AG20: The Office of Research Compliance and our Technology Transfer office handle these on a case-by-case basis. No automated tooling in place yet. | AH20: No | AI20: No | AJ20: Yes | AK20: No | AL20: IT Security provides general training but there is no dedicated open source security programme. Dependency scanning is not systematic. | AM20: No | AN20: Yes | AO20: No | AP20: Yes | AQ20: Yes | AR20: No | AS20: No | AT20: Procurement is managed through the central Purchasing office. IT maintains a software registry. Open source is generally preferred for research tools when support costs are manageable. | AU20: No | AV20: Yes | AW20: No | AX20: No | AY20: No | AZ20: No | BA20: Research outputs policy covers open source software publication. The review process is informal — typically through the PI and technology transfer office for anything with IP implications. | BB20: No | BC20: No | BD20: Yes | BE20: Yes | BF20: No | BG20: No | BH20: Research Services maintains a list of internally developed open source tools. The communications team occasionally promotes major releases but there is no structured programme. | BI20: Yes | BJ20: No | BK20: No | BL20: Yes | BM20: No | BN20: No | BO20: Yes | BP20: No | BQ20: No | BR20: IT provides GitHub organisation accounts and CI/CD via GitHub Actions. Research Services tracks citation counts for published software through our research outputs system. | BS20: Yes | BT20: Yes | BU20: No | BV20: Yes | BW20: No | BX20: No | BY20: No | BZ20: No | CA20: Senior leadership supports open source in principle and the connection to research mission is understood. However there is no formal strategy document or dedicated open source budget — funding comes through individual grants. | CC20: Yes | CD20: No | CE20: No | CF20: Yes | CG20: Yes | CH20: No | CI20: No | CJ20: Template language for data management plans that covers open source licensing obligations would be very useful. | CK20: Yes | CL20: No | CM20: Yes | CN20: No | CO20: A decision framework for evaluating open source vs commercial tools for research infrastructure would be very helpful. | CP20: No | CQ20: Yes | CR20: Yes | CS20: No | CT20: No | CU20: Researchers often ask us how to release code developed under a grant — a clear step-by-step guide would reduce the burden on our office. | CV20: Yes | CW20: No | CX20: No | CY20: Yes | CZ20: No | DA20: Regular cross-departmental sessions on open source tools used in research administration would help build institutional knowledge. | DB20: Yes | DC20: Yes | DD20: Yes | DE20: No | DF20: No | DG20: Post-grant sustainability is our biggest gap. Most software development funding ends with the grant — we need mechanisms to bridge to the next funding cycle. | DH20: Yes | DI20: No | DJ20: No | DK20: No | DL20: Yes | DM20: Yes | DN20: No | DO20: No | DP20: No | DQ20: Centralised storage for research software outputs that survives project end dates would address a key gap we currently face. | DR20: Yes | DS20: No | DT20: No | DU20: Yes | DV20: Yes | DW20: No | DX20: Being able to demonstrate the research impact and citation value of open source software would help us make the case to leadership for sustained investment. | DZ20: Yes | EA20: Yes | EB20: Yes | EC20: No | ED20: No | EE20: No | EG20: No | EH20: No | EI20: No | EJ20: No | EK20: No | EL20: Yes | EM20: No | EN20: Yes | EO20: No | EP20: No | EQ20: No | ER20: No | ES20: Yes | ET20: No | EU20: No | EV20: Yes | EW20: No | EX20: No | EY20: No | FA20: Yes | FB20: No | FC20: Yes | FD20: No | FE20: No | FF20: Yes | FG20: No | FH20: No | FI20: No | FK20: No | FL20: Yes | FM20: No | FN20: No | FO20: Yes | FP20: No | FQ20: No | FS20: No | FT20: No | FU20: No | FV20: No | FW20: No | FX20: No | FY20: No | FZ20: No | GA20: No | GB20: No | GC20: No | GD20: Yes | GE20: Yes | GF20: Yes | GG20: No | GI20: The survey covers the right territory. From a research administration perspective, the funding and sustainability section resonates most strongly — this is where we feel most underserved. It would also be helpful to distinguish between supporting researchers who use open source vs. those who create it, as the needs are quite different.

Sheet Item results (auto)
A1: Code | B1: Survey item | C1: Section | D1: OSMM level | E1: Service # | F1: % ticked (auto) | G1: Check
A2: Q300·SQ001 | B2: Has an open source program office (OSPO) or equivalent function | C2: Maturity | D2: L2 | E2: 1 | F2: =IF($I2=0,"",IF(COUNTIF(OFFSET('Data (paste export here)'!$B$1,1,0,100000,1),"<>")=0,"",ROUND(COUNTIFS(OFFSET('Data (paste export here)'!$A$1,1,$I2-1,100000,1),"Yes",OFFSET('Data (paste export here)'!$B$1,1,0,100000,1),"<>")/COUNTIF(OFFSET('Data (paste export here)'!$B$1,1,0,100000,1),"<>")*100,0))) | G2: =IF(AND($I2>0,ISNUMBER(SEARCH($J2,INDEX('Data (paste export here)'!$1:$1,$I2)))),"✓","✗") | H2: Q300[SQ001] | I2: =SUMPRODUCT((--ISNUMBER(SEARCH($H2,'Data (paste export here)'!$A$1:$HZ$1)))*COLUMN('Data (paste export here)'!$A$1:$HZ$1)) | J2: Has an open source program office (OSPO) or equivalent function | K2: Q300
A3: Q300·SQ002 | B3: Has an open source use policy | C3: Maturity | D3: L2 | E3: 4 | F3: =IF($I3=0,"",IF(COUNTIF(OFFSET('Data (paste export here)'!$B$1,1,0,100000,1),"<>")=0,"",ROUND(COUNTIFS(OFFSET('Data (paste export here)'!$A$1,1,$I3-1,100000,1),"Yes",OFFSET('Data (paste export here)'!$B$1,1,0,100000,1),"<>")/COUNTIF(OFFSET('Data (paste export here)'!$B$1,1,0,100000,1),"<>")*100,0))) | G3: =IF(AND($I3>0,ISNUMBER(SEARCH($J3,INDEX('Data (paste export here)'!$1:$1,$I3)))),"✓","✗") | H3: Q300[SQ002] | I3: =SUMPRODUCT((--ISNUMBER(SEARCH($H3,'Data (paste export here)'!$A$1:$HZ$1)))*COLUMN('Data (paste export here)'!$A$1:$HZ$1)) | J3: Has an open source use policy | K3: Q300
A4: Q300·SQ003 | B4: Has a defined process for using open source software | C4: Maturity | D4: L2 | E4: 6 | F4: =IF($I4=0,"",IF(COUNTIF(OFFSET('Data (paste export here)'!$B$1,1,0,100000,1),"<>")=0,"",ROUND(COUNTIFS(OFFSET('Data (paste export here)'!$A$1,1,$I4-1,100000,1),"Yes",OFFSET('Data (paste export here)'!$B$1,1,0,100000,1),"<>")/COUNTIF(OFFSET('Data (paste export here)'!$B$1,1,0,100000,1),"<>")*100,0))) | G4: =IF(AND($I4>0,ISNUMBER(SEARCH($J4,INDEX('Data (paste export here)'!$1:$1,$I4)))),"✓","✗") | H4: Q300[SQ003] | I4: =SUMPRODUCT((--ISNUMBER(SEARCH($H4,'Data (paste export here)'!$A$1:$HZ$1)))*COLUMN('Data (paste export here)'!$A$1:$HZ$1)) | J4: Has a defined process for using open source software | K4: Q300
A5: Q300·SQ004 | B5: Provides staff with guidance on the responsible use of open source AI | C5: Maturity | D5: L2 | E5: 13 | F5: =IF($I5=0,"",IF(COUNTIF(OFFSET('Data (paste export here)'!$B$1,1,0,100000,1),"<>")=0,"",ROUND(COUNTIFS(OFFSET('Data (paste export here)'!$A$1,1,$I5-1,100000,1),"Yes",OFFSET('Data (paste export here)'!$B$1,1,0,100000,1),"<>")/COUNTIF(OFFSET('Data (paste export here)'!$B$1,1,0,100000,1),"<>")*100,0))) | G5: =IF(AND($I5>0,ISNUMBER(SEARCH($J5,INDEX('Data (paste export here)'!$1:$1,$I5)))),"✓","✗") | H5: Q300[SQ004] | I5: =SUMPRODUCT((--ISNUMBER(SEARCH($H5,'Data (paste export here)'!$A$1:$HZ$1)))*COLUMN('Data (paste export here)'!$A$1:$HZ$1)) | J5: Provides staff with guidance on the responsible use of open source AI | K5: Q300
A6: Q310·SQ001 | B6: Has standardized controls around open source use | C6: Maturity | D6: L2 | E6: 4 | F6: =IF($I6=0,"",IF(COUNTIF(OFFSET('Data (paste export here)'!$B$1,1,0,100000,1),"<>")=0,"",ROUND(COUNTIFS(OFFSET('Data (paste export here)'!$A$1,1,$I6-1,100000,1),"Yes",OFFSET('Data (paste export here)'!$B$1,1,0,100000,1),"<>")/COUNTIF(OFFSET('Data (paste export here)'!$B$1,1,0,100000,1),"<>")*100,0))) | G6: =IF(AND($I6>0,ISNUMBER(SEARCH($J6,INDEX('Data (paste export here)'!$1:$1,$I6)))),"✓","✗") | H6: Q310[SQ001] | I6: =SUMPRODUCT((--ISNUMBER(SEARCH($H6,'Data (paste export here)'!$A$1:$HZ$1)))*COLUMN('Data (paste export here)'!$A$1:$HZ$1)) | J6: Has standardized controls around open source use | K6: Q310
A7: Q310·SQ002 | B7: Has an automated process for managing open source IP / license compliance | C7: Maturity | D7: L2 | E7: 4 | F7: =IF($I7=0,"",IF(COUNTIF(OFFSET('Data (paste export here)'!$B$1,1,0,100000,1),"<>")=0,"",ROUND(COUNTIFS(OFFSET('Data (paste export here)'!$A$1,1,$I7-1,100000,1),"Yes",OFFSET('Data (paste export here)'!$B$1,1,0,100000,1),"<>")/COUNTIF(OFFSET('Data (paste export here)'!$B$1,1,0,100000,1),"<>")*100,0))) | G7: =IF(AND($I7>0,ISNUMBER(SEARCH($J7,INDEX('Data (paste export here)'!$1:$1,$I7)))),"✓","✗") | H7: Q310[SQ002] | I7: =SUMPRODUCT((--ISNUMBER(SEARCH($H7,'Data (paste export here)'!$A$1:$HZ$1)))*COLUMN('Data (paste export here)'!$A$1:$HZ$1)) | J7: Has an automated process for managing open source IP / license compliance | K7: Q310
A8: Q310·SQ003 | B8: Includes open source risk management in its compliance policy | C8: Maturity | D8: L2 | E8: 5 | F8: =IF($I8=0,"",IF(COUNTIF(OFFSET('Data (paste export here)'!$B$1,1,0,100000,1),"<>")=0,"",ROUND(COUNTIFS(OFFSET('Data (paste export here)'!$A$1,1,$I8-1,100000,1),"Yes",OFFSET('Data (paste export here)'!$B$1,1,0,100000,1),"<>")/COUNTIF(OFFSET('Data (paste export here)'!$B$1,1,0,100000,1),"<>")*100,0))) | G8: =IF(AND($I8>0,ISNUMBER(SEARCH($J8,INDEX('Data (paste export here)'!$1:$1,$I8)))),"✓","✗") | H8: Q310[SQ003] | I8: =SUMPRODUCT((--ISNUMBER(SEARCH($H8,'Data (paste export here)'!$A$1:$HZ$1)))*COLUMN('Data (paste export here)'!$A$1:$HZ$1)) | J8: Includes open source risk management in its compliance policy | K8: Q310
A9: Q310·SQ004 | B9: Engages its technology-transfer or knowledge-exchange office when releasing or licensing open source software | C9: Maturity | D9: L4 | E9: 7 | F9: =IF($I9=0,"",IF(COUNTIF(OFFSET('Data (paste export here)'!$B$1,1,0,100000,1),"<>")=0,"",ROUND(COUNTIFS(OFFSET('Data (paste export here)'!$A$1,1,$I9-1,100000,1),"Yes",OFFSET('Data (paste export here)'!$B$1,1,0,100000,1),"<>")/COUNTIF(OFFSET('Data (paste export here)'!$B$1,1,0,100000,1),"<>")*100,0))) | G9: =IF(AND($I9>0,ISNUMBER(SEARCH($J9,INDEX('Data (paste export here)'!$1:$1,$I9)))),"✓","✗") | H9: Q310[SQ004] | I9: =SUMPRODUCT((--ISNUMBER(SEARCH($H9,'Data (paste export here)'!$A$1:$HZ$1)))*COLUMN('Data (paste export here)'!$A$1:$HZ$1)) | J9: Engages its technology-transfer or knowledge-exchange office when releasing or licensing open source software | K9: Q310
A10: Q310·SQ005 | B10: Provides internal license-compliance training | C10: Maturity | D10: L2 | E10: 4 | F10: =IF($I10=0,"",IF(COUNTIF(OFFSET('Data (paste export here)'!$B$1,1,0,100000,1),"<>")=0,"",ROUND(COUNTIFS(OFFSET('Data (paste export here)'!$A$1,1,$I10-1,100000,1),"Yes",OFFSET('Data (paste export here)'!$B$1,1,0,100000,1),"<>")/COUNTIF(OFFSET('Data (paste export here)'!$B$1,1,0,100000,1),"<>")*100,0))) | G10: =IF(AND($I10>0,ISNUMBER(SEARCH($J10,INDEX('Data (paste export here)'!$1:$1,$I10)))),"✓","✗") | H10: Q310[SQ005] | I10: =SUMPRODUCT((--ISNUMBER(SEARCH($H10,'Data (paste export here)'!$A$1:$HZ$1)))*COLUMN('Data (paste export here)'!$A$1:$HZ$1)) | J10: Provides internal license-compliance training | K10: Q310
A11: Q310·SQ006 | B11: Addresses AI-generated code (licensing, attribution, and IP) in its open source or compliance policy | C11: Maturity | D11: L2 | E11: 13 | F11: =IF($I11=0,"",IF(COUNTIF(OFFSET('Data (paste export here)'!$B$1,1,0,100000,1),"<>")=0,"",ROUND(COUNTIFS(OFFSET('Data (paste export here)'!$A$1,1,$I11-1,100000,1),"Yes",OFFSET('Data (paste export here)'!$B$1,1,0,100000,1),"<>")/COUNTIF(OFFSET('Data (paste export here)'!$B$1,1,0,100000,1),"<>")*100,0))) | G11: =IF(AND($I11>0,ISNUMBER(SEARCH($J11,INDEX('Data (paste export here)'!$1:$1,$I11)))),"✓","✗") | H11: Q310[SQ006] | I11: =SUMPRODUCT((--ISNUMBER(SEARCH($H11,'Data (paste export here)'!$A$1:$HZ$1)))*COLUMN('Data (paste export here)'!$A$1:$HZ$1)) | J11: Addresses AI-generated code (licensing, attribution, and IP) in its open source or compliance policy | K11: Q310
A12: Q320·SQ001 | B12: Uses code-scanning tools to audit software composition and dependencies | C12: Maturity | D12: L2 | E12: 5 | F12: =IF($I12=0,"",IF(COUNTIF(OFFSET('Data (paste export here)'!$B$1,1,0,100000,1),"<>")=0,"",ROUND(COUNTIFS(OFFSET('Data (paste export here)'!$A$1,1,$I12-1,100000,1),"Yes",OFFSET('Data (paste export here)'!$B$1,1,0,100000,1),"<>")/COUNTIF(OFFSET('Data (paste export here)'!$B$1,1,0,100000,1),"<>")*100,0))) | G12: =IF(AND($I12>0,ISNUMBER(SEARCH($J12,INDEX('Data (paste export here)'!$1:$1,$I12)))),"✓","✗") | H12: Q320[SQ001] | I12: =SUMPRODUCT((--ISNUMBER(SEARCH($H12,'Data (paste export here)'!$A$1:$HZ$1)))*COLUMN('Data (paste export here)'!$A$1:$HZ$1)) | J12: Uses code-scanning tools to audit software composition and dependencies | K12: Q320
A13: Q320·SQ002 | B13: Runs penetration tests and periodic threat assessments for open source software | C13: Maturity | D13: L2 | E13: 5 | F13: =IF($I13=0,"",IF(COUNTIF(OFFSET('Data (paste export here)'!$B$1,1,0,100000,1),"<>")=0,"",ROUND(COUNTIFS(OFFSET('Data (paste export here)'!$A$1,1,$I13-1,100000,1),"Yes",OFFSET('Data (paste export here)'!$B$1,1,0,100000,1),"<>")/COUNTIF(OFFSET('Data (paste export here)'!$B$1,1,0,100000,1),"<>")*100,0))) | G13: =IF(AND($I13>0,ISNUMBER(SEARCH($J13,INDEX('Data (paste export here)'!$1:$1,$I13)))),"✓","✗") | H13: Q320[SQ002] | I13: =SUMPRODUCT((--ISNUMBER(SEARCH($H13,'Data (paste export here)'!$A$1:$HZ$1)))*COLUMN('Data (paste export here)'!$A$1:$HZ$1)) | J13: Runs penetration tests and periodic threat assessments for open source software | K13: Q320
... A45: Q370·SQ007 | B45: Formally allocates staff time to open source maintenance and contribution | C45: Maturity | D45: L4 | E45: 9 | F45: =IF($I45=0,"",IF(COUNTIF(OFFSET('Data (paste export here)'!$B$1,1,0,100000,1),"<>")=0,"",ROUND(COUNTIFS(OFFSET('Data (paste export here)'!$A$1,1,$I45-1,100000,1),"Yes",OFFSET('Data (paste export here)'!$B$1,1,0,100000,1),"<>")/COUNTIF(OFFSET('Data (paste export here)'!$B$1,1,0,100000,1),"<>")*100,0))) | G45: =IF(AND($I45>0,ISNUMBER(SEARCH($J45,INDEX('Data (paste export here)'!$1:$1,$I45)))),"✓","✗") | H45: Q370[SQ007] | I45: =SUMPRODUCT((--ISNUMBER(SEARCH($H45,'Data (paste export here)'!$A$1:$HZ$1)))*COLUMN('Data (paste export here)'!$A$1:$HZ$1)) | J45: Formally allocates staff time to open source maintenance and contribution | K45: Q370
A46: Q400·SQ001 | B46: Legal and open source licensing advice and support | C46: Support | E46: 4 | F46: =IF($I46=0,"",IF(COUNTIF(OFFSET('Data (paste export here)'!$B$1,1,0,100000,1),"<>")=0,"",ROUND(COUNTIFS(OFFSET('Data (paste export here)'!$A$1,1,$I46-1,100000,1),"Yes",OFFSET('Data (paste export here)'!$B$1,1,0,100000,1),"<>")/COUNTIF(OFFSET('Data (paste export here)'!$B$1,1,0,100000,1),"<>")*100,0))) | G46: =IF(AND($I46>0,ISNUMBER(SEARCH($J46,INDEX('Data (paste export here)'!$1:$1,$I46)))),"✓","✗") | H46: Q400[SQ001] | I46: =SUMPRODUCT((--ISNUMBER(SEARCH($H46,'Data (paste export here)'!$A$1:$HZ$1)))*COLUMN('Data (paste export here)'!$A$1:$HZ$1)) | J46: Legal and open source licensing advice and support | K46: Q400
A47: Q400·SQ002 | B47: Advice on security management | C47: Support | E47: 5 | F47: =IF($I47=0,"",IF(COUNTIF(OFFSET('Data (paste export here)'!$B$1,1,0,100000,1),"<>")=0,"",ROUND(COUNTIFS(OFFSET('Data (paste export here)'!$A$1,1,$I47-1,100000,1),"Yes",OFFSET('Data (paste export here)'!$B$1,1,0,100000,1),"<>")/COUNTIF(OFFSET('Data (paste export here)'!$B$1,1,0,100000,1),"<>")*100,0))) | G47: =IF(AND($I47>0,ISNUMBER(SEARCH($J47,INDEX('Data (paste export here)'!$1:$1,$I47)))),"✓","✗") | H47: Q400[SQ002] | I47: =SUMPRODUCT((--ISNUMBER(SEARCH($H47,'Data (paste export here)'!$A$1:$HZ$1)))*COLUMN('Data (paste export here)'!$A$1:$HZ$1)) | J47: Advice on security management | K47: Q400
A48: Q400·SQ003 | B48: Advice on dependency management | C48: Support | E48: 5 | F48: =IF($I48=0,"",IF(COUNTIF(OFFSET('Data (paste export here)'!$B$1,1,0,100000,1),"<>")=0,"",ROUND(COUNTIFS(OFFSET('Data (paste export here)'!$A$1,1,$I48-1,100000,1),"Yes",OFFSET('Data (paste export here)'!$B$1,1,0,100000,1),"<>")/COUNTIF(OFFSET('Data (paste export here)'!$B$1,1,0,100000,1),"<>")*100,0))) | G48: =IF(AND($I48>0,ISNUMBER(SEARCH($J48,INDEX('Data (paste export here)'!$1:$1,$I48)))),"✓","✗") | H48: Q400[SQ003] | I48: =SUMPRODUCT((--ISNUMBER(SEARCH($H48,'Data (paste export here)'!$A$1:$HZ$1)))*COLUMN('Data (paste export here)'!$A$1:$HZ$1)) | J48: Advice on dependency management | K48: Q400
A49: Q400·SQ004 | B49: Assessing vendor open source obligations (e.g. CRA compliance, software bills of materials) | C49: Support | E49: 5 | F49: =IF($I49=0,"",IF(COUNTIF(OFFSET('Data (paste export here)'!$B$1,1,0,100000,1),"<>")=0,"",ROUND(COUNTIFS(OFFSET('Data (paste export here)'!$A$1,1,$I49-1,100000,1),"Yes",OFFSET('Data (paste export here)'!$B$1,1,0,100000,1),"<>")/COUNTIF(OFFSET('Data (paste export here)'!$B$1,1,0,100000,1),"<>")*100,0))) | G49: =IF(AND($I49>0,ISNUMBER(SEARCH($J49,INDEX('Data (paste export here)'!$1:$1,$I49)))),"✓","✗") | H49: Q400[SQ004] | I49: =SUMPRODUCT((--ISNUMBER(SEARCH($H49,'Data (paste export here)'!$A$1:$HZ$1)))*COLUMN('Data (paste export here)'!$A$1:$HZ$1)) | J49: Assessing vendor open source obligations (e.g. CRA compliance, software bills of materials) | K49: Q400
A50: Q400·SQ005 | B50: Grant compliance with respect to open source requirements | C50: Support | E50: 9 | F50: =IF($I50=0,"",IF(COUNTIF(OFFSET('Data (paste export here)'!$B$1,1,0,100000,1),"<>")=0,"",ROUND(COUNTIFS(OFFSET('Data (paste export here)'!$A$1,1,$I50-1,100000,1),"Yes",OFFSET('Data (paste export here)'!$B$1,1,0,100000,1),"<>")/COUNTIF(OFFSET('Data (paste export here)'!$B$1,1,0,100000,1),"<>")*100,0))) | G50: =IF(AND($I50>0,ISNUMBER(SEARCH($J50,INDEX('Data (paste export here)'!$1:$1,$I50)))),"✓","✗") | H50: Q400[SQ005] | I50: =SUMPRODUCT((--ISNUMBER(SEARCH($H50,'Data (paste export here)'!$A$1:$HZ$1)))*COLUMN('Data (paste export here)'!$A$1:$HZ$1)) | J50: Grant compliance with respect to open source requirements | K50: Q400
A51: Q400·SQ006 | B51: Policy recommendations and best practices around open source AI | C51: Support | E51: 13 | F51: =IF($I51=0,"",IF(COUNTIF(OFFSET('Data (paste export here)'!$B$1,1,0,100000,1),"<>")=0,"",ROUND(COUNTIFS(OFFSET('Data (paste export here)'!$A$1,1,$I51-1,100000,1),"Yes",OFFSET('Data (paste export here)'!$B$1,1,0,100000,1),"<>")/COUNTIF(OFFSET('Data (paste export here)'!$B$1,1,0,100000,1),"<>")*100,0))) | G51: =IF(AND($I51>0,ISNUMBER(SEARCH($J51,INDEX('Data (paste export here)'!$1:$1,$I51)))),"✓","✗") | H51: Q400[SQ006] | I51: =SUMPRODUCT((--ISNUMBER(SEARCH($H51,'Data (paste export here)'!$A$1:$HZ$1)))*COLUMN('Data (paste export here)'!$A$1:$HZ$1)) | J51: Policy recommendations and best practices around open source AI | K51: Q400
A52: Q410·SQ001 | B52: Guidelines or policies for using open source software within UNO | C52: Support | E52: 6 | F52: =IF($I52=0,"",IF(COUNTIF(OFFSET('Data (paste export here)'!$B$1,1,0,100000,1),"<>")=0,"",ROUND(COUNTIFS(OFFSET('Data (paste export here)'!$A$1,1,$I52-1,100000,1),"Yes",OFFSET('Data (paste export here)'!$B$1,1,0,100000,1),"<>")/COUNTIF(OFFSET('Data (paste export here)'!$B$1,1,0,100000,1),"<>")*100,0))) | G52: =IF(AND($I52>0,ISNUMBER(SEARCH($J52,INDEX('Data (paste export here)'!$1:$1,$I52)))),"✓","✗") | H52: Q410[SQ001] | I52: =SUMPRODUCT((--ISNUMBER(SEARCH($H52,'Data (paste export here)'!$A$1:$HZ$1)))*COLUMN('Data (paste export here)'!$A$1:$HZ$1)) | J52: Guidelines or policies for using open source software within UNO | K52: Q410
A53: Q410·SQ002 | B53: Guidelines or policies for procuring open source software | C53: Support | E53: 6 | F53: =IF($I53=0,"",IF(COUNTIF(OFFSET('Data (paste export here)'!$B$1,1,0,100000,1),"<>")=0,"",ROUND(COUNTIFS(OFFSET('Data (paste export here)'!$A$1,1,$I53-1,100000,1),"Yes",OFFSET('Data (paste export here)'!$B$1,1,0,100000,1),"<>")/COUNTIF(OFFSET('Data (paste export here)'!$B$1,1,0,100000,1),"<>")*100,0))) | G53: =IF(AND($I53>0,ISNUMBER(SEARCH($J53,INDEX('Data (paste export here)'!$1:$1,$I53)))),"✓","✗") | H53: Q410[SQ002] | I53: =SUMPRODUCT((--ISNUMBER(SEARCH($H53,'Data (paste export here)'!$A$1:$HZ$1)))*COLUMN('Data (paste export here)'!$A$1:$HZ$1)) | J53: Guidelines or policies for procuring open source software | K53: Q410
A54: Q410·SQ003 | B54: A curated catalogue or directory of open source tools relevant to UNO's community | C54: Support | E54: 6 | F54: =IF($I54=0,"",IF(COUNTIF(OFFSET('Data (paste export here)'!$B$1,1,0,100000,1),"<>")=0,"",ROUND(COUNTIFS(OFFSET('Data (paste export here)'!$A$1,1,$I54-1,100000,1),"Yes",OFFSET('Data (paste export here)'!$B$1,1,0,100000,1),"<>")/COUNTIF(OFFSET('Data (paste export here)'!$B$1,1,0,100000,1),"<>")*100,0))) | G54: =IF(AND($I54>0,ISNUMBER(SEARCH($J54,INDEX('Data (paste export here)'!$1:$1,$I54)))),"✓","✗") | H54: Q410[SQ003] | I54: =SUMPRODUCT((--ISNUMBER(SEARCH($H54,'Data (paste export here)'!$A$1:$HZ$1)))*COLUMN('Data (paste export here)'!$A$1:$HZ$1)) | J54: A curated catalogue or directory of open source tools relevant to UNO's community | K54: Q410
A55: Q420·SQ001 | B55: Guidelines or policies on managing and maintaining an open source project | C55: Support | E55: 3 | F55: =IF($I55=0,"",IF(COUNTIF(OFFSET('Data (paste export here)'!$B$1,1,0,100000,1),"<>")=0,"",ROUND(COUNTIFS(OFFSET('Data (paste export here)'!$A$1,1,$I55-1,100000,1),"Yes",OFFSET('Data (paste export here)'!$B$1,1,0,100000,1),"<>")/COUNTIF(OFFSET('Data (paste export here)'!$B$1,1,0,100000,1),"<>")*100,0))) | G55: =IF(AND($I55>0,ISNUMBER(SEARCH($J55,INDEX('Data (paste export here)'!$1:$1,$I55)))),"✓","✗") | H55: Q420[SQ001] | I55: =SUMPRODUCT((--ISNUMBER(SEARCH($H55,'Data (paste export here)'!$A$1:$HZ$1)))*COLUMN('Data (paste export here)'!$A$1:$HZ$1)) | J55: Guidelines or policies on managing and maintaining an open source project | K55: Q420
A56: Q420·SQ002 | B56: Guidance on transitioning an internal project to open source | C56: Support | E56: 7 | F56: =IF($I56=0,"",IF(COUNTIF(OFFSET('Data (paste export here)'!$B$1,1,0,100000,1),"<>")=0,"",ROUND(COUNTIFS(OFFSET('Data (paste export here)'!$A$1,1,$I56-1,100000,1),"Yes",OFFSET('Data (paste export here)'!$B$1,1,0,100000,1),"<>")/COUNTIF(OFFSET('Data (paste export here)'!$B$1,1,0,100000,1),"<>")*100,0))) | G56: =IF(AND($I56>0,ISNUMBER(SEARCH($J56,INDEX('Data (paste export here)'!$1:$1,$I56)))),"✓","✗") | H56: Q420[SQ002] | I56: =SUMPRODUCT((--ISNUMBER(SEARCH($H56,'Data (paste export here)'!$A$1:$HZ$1)))*COLUMN('Data (paste export here)'!$A$1:$HZ$1)) | J56: Guidance on transitioning an internal project to open source | K56: Q420
A57: Q420·SQ003 | B57: Support writing documentation for open source projects | C57: Support | E57: 3 | F57: =IF($I57=0,"",IF(COUNTIF(OFFSET('Data (paste export here)'!$B$1,1,0,100000,1),"<>")=0,"",ROUND(COUNTIFS(OFFSET('Data (paste export here)'!$A$1,1,$I57-1,100000,1),"Yes",OFFSET('Data (paste export here)'!$B$1,1,0,100000,1),"<>")/COUNTIF(OFFSET('Data (paste export here)'!$B$1,1,0,100000,1),"<>")*100,0))) | G57: =IF(AND($I57>0,ISNUMBER(SEARCH($J57,INDEX('Data (paste export here)'!$1:$1,$I57)))),"✓","✗") | H57: Q420[SQ003] | I57: =SUMPRODUCT((--ISNUMBER(SEARCH($H57,'Data (paste export here)'!$A$1:$HZ$1)))*COLUMN('Data (paste export here)'!$A$1:$HZ$1)) | J57: Support writing documentation for open source projects | K57: Q420
... A79: Q460·SQ005 | B79: Support communicating or measuring the societal impact of my open source work | C79: Support | E79: 10 | F79: =IF($I79=0,"",IF(COUNTIF(OFFSET('Data (paste export here)'!$B$1,1,0,100000,1),"<>")=0,"",ROUND(COUNTIFS(OFFSET('Data (paste export here)'!$A$1,1,$I79-1,100000,1),"Yes",OFFSET('Data (paste export here)'!$B$1,1,0,100000,1),"<>")/COUNTIF(OFFSET('Data (paste export here)'!$B$1,1,0,100000,1),"<>")*100,0))) | G79: =IF(AND($I79>0,ISNUMBER(SEARCH($J79,INDEX('Data (paste export here)'!$1:$1,$I79)))),"✓","✗") | H79: Q460[SQ005] | I79: =SUMPRODUCT((--ISNUMBER(SEARCH($H79,'Data (paste export here)'!$A$1:$HZ$1)))*COLUMN('Data (paste export here)'!$A$1:$HZ$1)) | J79: Support communicating or measuring the societal impact of my open source work | K79: Q460

Sheet Service summary
A1: # | B1: Academic OSPO service | C1: Maturity % | D1: Demand % | E1: Gap (Demand − Maturity)
A2: 1 | B2: OSPO Strategy & Vision | C2: =IFERROR(AVERAGEIFS('Item results (auto)'!$F$2:$F$79,'Item results (auto)'!$E$2:$E$79,$A2,'Item results (auto)'!$C$2:$C$79,"Maturity"),"") | D2: =IFERROR(AVERAGEIFS('Item results (auto)'!$F$2:$F$79,'Item results (auto)'!$E$2:$E$79,$A2,'Item results (auto)'!$C$2:$C$79,"Support"),"") | E2: =IF(OR($D2="",$C2=""),"—",$D2-$C2)
A3: 2 | B3: Community of Practice | C3: =IFERROR(AVERAGEIFS('Item results (auto)'!$F$2:$F$79,'Item results (auto)'!$E$2:$E$79,$A3,'Item results (auto)'!$C$2:$C$79,"Maturity"),"") | D3: =IFERROR(AVERAGEIFS('Item results (auto)'!$F$2:$F$79,'Item results (auto)'!$E$2:$E$79,$A3,'Item results (auto)'!$C$2:$C$79,"Support"),"") | E3: =IF(OR($D3="",$C3=""),"—",$D3-$C3)
A4: 3 | B4: Project Lifecycle Support & Maintenance | C4: =IFERROR(AVERAGEIFS('Item results (auto)'!$F$2:$F$79,'Item results (auto)'!$E$2:$E$79,$A4,'Item results (auto)'!$C$2:$C$79,"Maturity"),"") | D4: =IFERROR(AVERAGEIFS('Item results (auto)'!$F$2:$F$79,'Item results (auto)'!$E$2:$E$79,$A4,'Item results (auto)'!$C$2:$C$79,"Support"),"") | E4: =IF(OR($D4="",$C4=""),"—",$D4-$C4)
A5: 4 | B5: License & IPR Compliance | C5: =IFERROR(AVERAGEIFS('Item results (auto)'!$F$2:$F$79,'Item results (auto)'!$E$2:$E$79,$A5,'Item results (auto)'!$C$2:$C$79,"Maturity"),"") | D5: =IFERROR(AVERAGEIFS('Item results (auto)'!$F$2:$F$79,'Item results (auto)'!$E$2:$E$79,$A5,'Item results (auto)'!$C$2:$C$79,"Support"),"") | E5: =IF(OR($D5="",$C5=""),"—",$D5-$C5)
A6: 5 | B6: Supply-Chain Security & SBOM | C6: =IFERROR(AVERAGEIFS('Item results (auto)'!$F$2:$F$79,'Item results (auto)'!$E$2:$E$79,$A6,'Item results (auto)'!$C$2:$C$79,"Maturity"),"") | D6: =IFERROR(AVERAGEIFS('Item results (auto)'!$F$2:$F$79,'Item results (auto)'!$E$2:$E$79,$A6,'Item results (auto)'!$C$2:$C$79,"Support"),"") | E6: =IF(OR($D6="",$C6=""),"—",$D6-$C6)
A7: 6 | B7: Choosing, Using & Procuring Open Source | C7: =IFERROR(AVERAGEIFS('Item results (auto)'!$F$2:$F$79,'Item results (auto)'!$E$2:$E$79,$A7,'Item results (auto)'!$C$2:$C$79,"Maturity"),"") | D7: =IFERROR(AVERAGEIFS('Item results (auto)'!$F$2:$F$79,'Item results (auto)'!$E$2:$E$79,$A7,'Item results (auto)'!$C$2:$C$79,"Support"),"") | E7: =IF(OR($D7="",$C7=""),"—",$D7-$C7)
A8: 7 | B8: Open-Sourcing Guidance | C8: =IFERROR(AVERAGEIFS('Item results (auto)'!$F$2:$F$79,'Item results (auto)'!$E$2:$E$79,$A8,'Item results (auto)'!$C$2:$C$79,"Maturity"),"") | D8: =IFERROR(AVERAGEIFS('Item results (auto)'!$F$2:$F$79,'Item results (auto)'!$E$2:$E$79,$A8,'Item results (auto)'!$C$2:$C$79,"Support"),"") | E8: =IF(OR($D8="",$C8=""),"—",$D8-$C8)
A9: 8 | B9: Internal Advocacy & Buy-In | C9: =IFERROR(AVERAGEIFS('Item results (auto)'!$F$2:$F$79,'Item results (auto)'!$E$2:$E$79,$A9,'Item results (auto)'!$C$2:$C$79,"Maturity"),"") | D9: =IFERROR(AVERAGEIFS('Item results (auto)'!$F$2:$F$79,'Item results (auto)'!$E$2:$E$79,$A9,'Item results (auto)'!$C$2:$C$79,"Support"),"") | E9: =IF(OR($D9="",$C9=""),"—",$D9-$C9)
A10: 9 | B10: Sustainability & Funding Support | C10: =IFERROR(AVERAGEIFS('Item results (auto)'!$F$2:$F$79,'Item results (auto)'!$E$2:$E$79,$A10,'Item results (auto)'!$C$2:$C$79,"Maturity"),"") | D10: =IFERROR(AVERAGEIFS('Item results (auto)'!$F$2:$F$79,'Item results (auto)'!$E$2:$E$79,$A10,'Item results (auto)'!$C$2:$C$79,"Support"),"") | E10: =IF(OR($D10="",$C10=""),"—",$D10-$C10)
A11: 10 | B11: Impact Measurement | C11: =IFERROR(AVERAGEIFS('Item results (auto)'!$F$2:$F$79,'Item results (auto)'!$E$2:$E$79,$A11,'Item results (auto)'!$C$2:$C$79,"Maturity"),"") | D11: =IFERROR(AVERAGEIFS('Item results (auto)'!$F$2:$F$79,'Item results (auto)'!$E$2:$E$79,$A11,'Item results (auto)'!$C$2:$C$79,"Support"),"") | E11: =IF(OR($D11="",$C11=""),"—",$D11-$C11)
A12: 11 | B12: Developer Tooling & Infrastructure | C12: =IFERROR(AVERAGEIFS('Item results (auto)'!$F$2:$F$79,'Item results (auto)'!$E$2:$E$79,$A12,'Item results (auto)'!$C$2:$C$79,"Maturity"),"") | D12: =IFERROR(AVERAGEIFS('Item results (auto)'!$F$2:$F$79,'Item results (auto)'!$E$2:$E$79,$A12,'Item results (auto)'!$C$2:$C$79,"Support"),"") | E12: =IF(OR($D12="",$C12=""),"—",$D12-$C12)
A13: 12 | B13: Outreach & Events | C13: =IFERROR(AVERAGEIFS('Item results (auto)'!$F$2:$F$79,'Item results (auto)'!$E$2:$E$79,$A13,'Item results (auto)'!$C$2:$C$79,"Maturity"),"") | D13: =IFERROR(AVERAGEIFS('Item results (auto)'!$F$2:$F$79,'Item results (auto)'!$E$2:$E$79,$A13,'Item results (auto)'!$C$2:$C$79,"Support"),"") | E13: =IF(OR($D13="",$C13=""),"—",$D13-$C13)
A14: 13 | B14: Open Source AI Policy | C14: =IFERROR(AVERAGEIFS('Item results (auto)'!$F$2:$F$79,'Item results (auto)'!$E$2:$E$79,$A14,'Item results (auto)'!$C$2:$C$79,"Maturity"),"") | D14: =IFERROR(AVERAGEIFS('Item results (auto)'!$F$2:$F$79,'Item results (auto)'!$E$2:$E$79,$A14,'Item results (auto)'!$C$2:$C$79,"Support"),"") | E14: =IF(OR($D14="",$C14=""),"—",$D14-$C14)

Sheet Level summary
A1: OSMM level | B1: What it covers | C1: Maturity %
A2: L2 | B2: Compliant usage — governance, policy, compliance, security | C2: =IFERROR(AVERAGEIFS('Item results (auto)'!$F$2:$F$79,'Item results (auto)'!$C$2:$C$79,"Maturity",'Item results (auto)'!$D$2:$D$79,$A2),"")
A3: L3 | B3: Contribution — publishing, reviewing, rewarding | C3: =IFERROR(AVERAGEIFS('Item results (auto)'!$F$2:$F$79,'Item results (auto)'!$C$2:$C$79,"Maturity",'Item results (auto)'!$D$2:$D$79,$A3),"")
A4: L4 | B4: Engagement & hosting — maintains projects, foundations, metrics | C4: =IFERROR(AVERAGEIFS('Item results (auto)'!$F$2:$F$79,'Item results (auto)'!$C$2:$C$79,"Maturity",'Item results (auto)'!$D$2:$D$79,$A4),"")
A5: L5 | B5: Leadership & strategy — strategy, sustainability, mission | C5: =IFERROR(AVERAGEIFS('Item results (auto)'!$F$2:$F$79,'Item results (auto)'!$C$2:$C$79,"Maturity",'Item results (auto)'!$D$2:$D$79,$A5),"")

Sheet Write-ins
A1: Write-in comments
A2: Each row gathers the non-empty free-text answers for one question (joined with •). Pulled live from the pasted data.
A4: Topic | B4: # responses | C4: Comments
A5: Respondent's unit / department | B5: =COUNTA(OFFSET('Data (paste export here)'!$A$1,1,SUMPRODUCT((--ISNUMBER(SEARCH("Q10[comment]",'Data (paste export here)'!$A$1:$HZ$1)))*COLUMN('Data (paste export here)'!$A$1:$HZ$1))-1,10000,1)) | C5: =_xlfn.TEXTJOIN(" • ",TRUE(),OFFSET('Data (paste export here)'!$A$1,1,SUMPRODUCT((--ISNUMBER(SEARCH("Q10[comment]",'Data (paste export here)'!$A$1:$HZ$1)))*COLUMN('Data (paste export here)'!$A$1:$HZ$1))-1,10000,1))
A6: Where support lives — Policy & OSPO | B6: =COUNTA(OFFSET('Data (paste export here)'!$A$1,1,SUMPRODUCT((--ISNUMBER(SEARCH("Q301.",'Data (paste export here)'!$A$1:$HZ$1)))*COLUMN('Data (paste export here)'!$A$1:$HZ$1))-1,10000,1)) | C6: =_xlfn.TEXTJOIN(" • ",TRUE(),OFFSET('Data (paste export here)'!$A$1,1,SUMPRODUCT((--ISNUMBER(SEARCH("Q301.",'Data (paste export here)'!$A$1:$HZ$1)))*COLUMN('Data (paste export here)'!$A$1:$HZ$1))-1,10000,1))
A7: Where support lives — Compliance and risk | B7: =COUNTA(OFFSET('Data (paste export here)'!$A$1,1,SUMPRODUCT((--ISNUMBER(SEARCH("Q311.",'Data (paste export here)'!$A$1:$HZ$1)))*COLUMN('Data (paste export here)'!$A$1:$HZ$1))-1,10000,1)) | C7: =_xlfn.TEXTJOIN(" • ",TRUE(),OFFSET('Data (paste export here)'!$A$1,1,SUMPRODUCT((--ISNUMBER(SEARCH("Q311.",'Data (paste export here)'!$A$1:$HZ$1)))*COLUMN('Data (paste export here)'!$A$1:$HZ$1))-1,10000,1))
A8: Where support lives — Security & supply chain | B8: =COUNTA(OFFSET('Data (paste export here)'!$A$1,1,SUMPRODUCT((--ISNUMBER(SEARCH("Q321.",'Data (paste export here)'!$A$1:$HZ$1)))*COLUMN('Data (paste export here)'!$A$1:$HZ$1))-1,10000,1)) | C8: =_xlfn.TEXTJOIN(" • ",TRUE(),OFFSET('Data (paste export here)'!$A$1,1,SUMPRODUCT((--ISNUMBER(SEARCH("Q321.",'Data (paste export here)'!$A$1:$HZ$1)))*COLUMN('Data (paste export here)'!$A$1:$HZ$1))-1,10000,1))
A9: Where support lives — Selection, use & procurement | B9: =COUNTA(OFFSET('Data (paste export here)'!$A$1,1,SUMPRODUCT((--ISNUMBER(SEARCH("Q331.",'Data (paste export here)'!$A$1:$HZ$1)))*COLUMN('Data (paste export here)'!$A$1:$HZ$1))-1,10000,1)) | C9: =_xlfn.TEXTJOIN(" • ",TRUE(),OFFSET('Data (paste export here)'!$A$1,1,SUMPRODUCT((--ISNUMBER(SEARCH("Q331.",'Data (paste export here)'!$A$1:$HZ$1)))*COLUMN('Data (paste export here)'!$A$1:$HZ$1))-1,10000,1))
A10: Where support lives — Open source contribution | B10: =COUNTA(OFFSET('Data (paste export here)'!$A$1,1,SUMPRODUCT((--ISNUMBER(SEARCH("Q341.",'Data (paste export here)'!$A$1:$HZ$1)))*COLUMN('Data (paste export here)'!$A$1:$HZ$1))-1,10000,1)) | C10: =_xlfn.TEXTJOIN(" • ",TRUE(),OFFSET('Data (paste export here)'!$A$1,1,SUMPRODUCT((--ISNUMBER(SEARCH("Q341.",'Data (paste export here)'!$A$1:$HZ$1)))*COLUMN('Data (paste export here)'!$A$1:$HZ$1))-1,10000,1))
A11: Where support lives — Community and outreach | B11: =COUNTA(OFFSET('Data (paste export here)'!$A$1,1,SUMPRODUCT((--ISNUMBER(SEARCH("Q351.",'Data (paste export here)'!$A$1:$HZ$1)))*COLUMN('Data (paste export here)'!$A$1:$HZ$1))-1,10000,1)) | C11: =_xlfn.TEXTJOIN(" • ",TRUE(),OFFSET('Data (paste export here)'!$A$1,1,SUMPRODUCT((--ISNUMBER(SEARCH("Q351.",'Data (paste export here)'!$A$1:$HZ$1)))*COLUMN('Data (paste export here)'!$A$1:$HZ$1))-1,10000,1))
A12: Where support lives — Hosting and maintenance | B12: =COUNTA(OFFSET('Data (paste export here)'!$A$1,1,SUMPRODUCT((--ISNUMBER(SEARCH("Q361.",'Data (paste export here)'!$A$1:$HZ$1)))*COLUMN('Data (paste export here)'!$A$1:$HZ$1))-1,10000,1)) | C12: =_xlfn.TEXTJOIN(" • ",TRUE(),OFFSET('Data (paste export here)'!$A$1,1,SUMPRODUCT((--ISNUMBER(SEARCH("Q361.",'Data (paste export here)'!$A$1:$HZ$1)))*COLUMN('Data (paste export here)'!$A$1:$HZ$1))-1,10000,1))
A13: Where support lives — Leadership and strategy | B13: =COUNTA(OFFSET('Data (paste export here)'!$A$1,1,SUMPRODUCT((--ISNUMBER(SEARCH("Q371.",'Data (paste export here)'!$A$1:$HZ$1)))*COLUMN('Data (paste export here)'!$A$1:$HZ$1))-1,10000,1)) | C13: =_xlfn.TEXTJOIN(" • ",TRUE(),OFFSET('Data (paste export here)'!$A$1,1,SUMPRODUCT((--ISNUMBER(SEARCH("Q371.",'Data (paste export here)'!$A$1:$HZ$1)))*COLUMN('Data (paste export here)'!$A$1:$HZ$1))-1,10000,1))
A14: Other support wanted — Legal, compliance & risk | B14: =COUNTA(OFFSET('Data (paste export here)'!$A$1,1,SUMPRODUCT((--ISNUMBER(SEARCH("Q401.",'Data (paste export here)'!$A$1:$HZ$1)))*COLUMN('Data (paste export here)'!$A$1:$HZ$1))-1,10000,1)) | C14: =_xlfn.TEXTJOIN(" • ",TRUE(),OFFSET('Data (paste export here)'!$A$1,1,SUMPRODUCT((--ISNUMBER(SEARCH("Q401.",'Data (paste export here)'!$A$1:$HZ$1)))*COLUMN('Data (paste export here)'!$A$1:$HZ$1))-1,10000,1))
A15: Other support wanted — Selection, use & procurement | B15: =COUNTA(OFFSET('Data (paste export here)'!$A$1,1,SUMPRODUCT((--ISNUMBER(SEARCH("Q411.",'Data (paste export here)'!$A$1:$HZ$1)))*COLUMN('Data (paste export here)'!$A$1:$HZ$1))-1,10000,1)) | C15: =_xlfn.TEXTJOIN(" • ",TRUE(),OFFSET('Data (paste export here)'!$A$1,1,SUMPRODUCT((--ISNUMBER(SEARCH("Q411.",'Data (paste export here)'!$A$1:$HZ$1)))*COLUMN('Data (paste export here)'!$A$1:$HZ$1))-1,10000,1))
A16: Other support wanted — Project creation & maintenance | B16: =COUNTA(OFFSET('Data (paste export here)'!$A$1,1,SUMPRODUCT((--ISNUMBER(SEARCH("Q421.",'Data (paste export here)'!$A$1:$HZ$1)))*COLUMN('Data (paste export here)'!$A$1:$HZ$1))-1,10000,1)) | C16: =_xlfn.TEXTJOIN(" • ",TRUE(),OFFSET('Data (paste export here)'!$A$1,1,SUMPRODUCT((--ISNUMBER(SEARCH("Q421.",'Data (paste export here)'!$A$1:$HZ$1)))*COLUMN('Data (paste export here)'!$A$1:$HZ$1))-1,10000,1))
A17: Other support wanted — Community & mentoring | B17: =COUNTA(OFFSET('Data (paste export here)'!$A$1,1,SUMPRODUCT((--ISNUMBER(SEARCH("Q431.",'Data (paste export here)'!$A$1:$HZ$1)))*COLUMN('Data (paste export here)'!$A$1:$HZ$1))-1,10000,1)) | C17: =_xlfn.TEXTJOIN(" • ",TRUE(),OFFSET('Data (paste export here)'!$A$1,1,SUMPRODUCT((--ISNUMBER(SEARCH("Q431.",'Data (paste export here)'!$A$1:$HZ$1)))*COLUMN('Data (paste export here)'!$A$1:$HZ$1))-1,10000,1))
A18: Other support wanted — Funding & sustainability | B18: =COUNTA(OFFSET('Data (paste export here)'!$A$1,1,SUMPRODUCT((--ISNUMBER(SEARCH("Q441.",'Data (paste export here)'!$A$1:$HZ$1)))*COLUMN('Data (paste export here)'!$A$1:$HZ$1))-1,10000,1)) | C18: =_xlfn.TEXTJOIN(" • ",TRUE(),OFFSET('Data (paste export here)'!$A$1,1,SUMPRODUCT((--ISNUMBER(SEARCH("Q441.",'Data (paste export here)'!$A$1:$HZ$1)))*COLUMN('Data (paste export here)'!$A$1:$HZ$1))-1,10000,1))
A19: Other support wanted — Tools & compute resources | B19: =COUNTA(OFFSET('Data (paste export here)'!$A$1,1,SUMPRODUCT((--ISNUMBER(SEARCH("Q451.",'Data (paste export here)'!$A$1:$HZ$1)))*COLUMN('Data (paste export here)'!$A$1:$HZ$1))-1,10000,1)) | C19: =_xlfn.TEXTJOIN(" • ",TRUE(),OFFSET('Data (paste export here)'!$A$1,1,SUMPRODUCT((--ISNUMBER(SEARCH("Q451.",'Data (paste export here)'!$A$1:$HZ$1)))*COLUMN('Data (paste export here)'!$A$1:$HZ$1))-1,10000,1))
A20: Other support wanted — Advocacy & outreach | B20: =COUNTA(OFFSET('Data (paste export here)'!$A$1,1,SUMPRODUCT((--ISNUMBER(SEARCH("Q461.",'Data (paste export here)'!$A$1:$HZ$1)))*COLUMN('Data (paste export here)'!$A$1:$HZ$1))-1,10000,1)) | C20: =_xlfn.TEXTJOIN(" • ",TRUE(),OFFSET('Data (paste export here)'!$A$1,1,SUMPRODUCT((--ISNUMBER(SEARCH("Q461.",'Data (paste export here)'!$A$1:$HZ$1)))*COLUMN('Data (paste export here)'!$A$1:$HZ$1))-1,10000,1))
A21: Final feedback / anything missed | B21: =COUNTA(OFFSET('Data (paste export here)'!$A$1,1,SUMPRODUCT((--ISNUMBER(SEARCH("Q70.",'Data (paste export here)'!$A$1:$HZ$1)))*COLUMN('Data (paste export here)'!$A$1:$HZ$1))-1,10000,1)) | C21: =_xlfn.TEXTJOIN(" • ",TRUE(),OFFSET('Data (paste export here)'!$A$1,1,SUMPRODUCT((--ISNUMBER(SEARCH("Q70.",'Data (paste export here)'!$A$1:$HZ$1)))*COLUMN('Data (paste export here)'!$A$1:$HZ$1))-1,10000,1))

Sheet Respondents
A1: Respondents
A3: Role (Q10)
A4: Answer | B4: Count | C4: %
A5: Leadership / Administration | B5: =COUNTIFS(OFFSET('Data (paste export here)'!$A$1,1,SUMPRODUCT((--ISNUMBER(SEARCH("Q10.",'Data (paste export here)'!$A$1:$HZ$1)))*COLUMN('Data (paste export here)'!$A$1:$HZ$1))-1,10000,1),$A5,OFFSET('Data (paste export here)'!$B$1,1,0,10000,1),"<>") | C5: =IF(COUNTIF(OFFSET('Data (paste export here)'!$B$1,1,0,10000,1),"<>")=0,"",ROUND(B5/COUNTIF(OFFSET('Data (paste export here)'!$B$1,1,0,10000,1),"<>")*100,0))
A6: Faculty / Academic staff | B6: =COUNTIFS(OFFSET('Data (paste export here)'!$A$1,1,SUMPRODUCT((--ISNUMBER(SEARCH("Q10.",'Data (paste export here)'!$A$1:$HZ$1)))*COLUMN('Data (paste export here)'!$A$1:$HZ$1))-1,10000,1),$A6,OFFSET('Data (paste export here)'!$B$1,1,0,10000,1),"<>") | C6: =IF(COUNTIF(OFFSET('Data (paste export here)'!$B$1,1,0,10000,1),"<>")=0,"",ROUND(B6/COUNTIF(OFFSET('Data (paste export here)'!$B$1,1,0,10000,1),"<>")*100,0))
A7: Research staff (postdocs, research software engineers) | B7: =COUNTIFS(OFFSET('Data (paste export here)'!$A$1,1,SUMPRODUCT((--ISNUMBER(SEARCH("Q10.",'Data (paste export here)'!$A$1:$HZ$1)))*COLUMN('Data (paste export here)'!$A$1:$HZ$1))-1,10000,1),$A7,OFFSET('Data (paste export here)'!$B$1,1,0,10000,1),"<>") | C7: =IF(COUNTIF(OFFSET('Data (paste export here)'!$B$1,1,0,10000,1),"<>")=0,"",ROUND(B7/COUNTIF(OFFSET('Data (paste export here)'!$B$1,1,0,10000,1),"<>")*100,0))
A8: Professional / Support staff (including IT and library) | B8: =COUNTIFS(OFFSET('Data (paste export here)'!$A$1,1,SUMPRODUCT((--ISNUMBER(SEARCH("Q10.",'Data (paste export here)'!$A$1:$HZ$1)))*COLUMN('Data (paste export here)'!$A$1:$HZ$1))-1,10000,1),$A8,OFFSET('Data (paste export here)'!$B$1,1,0,10000,1),"<>") | C8: =IF(COUNTIF(OFFSET('Data (paste export here)'!$B$1,1,0,10000,1),"<>")=0,"",ROUND(B8/COUNTIF(OFFSET('Data (paste export here)'!$B$1,1,0,10000,1),"<>")*100,0))
A9: Student (graduate or undergraduate) | B9: =COUNTIFS(OFFSET('Data (paste export here)'!$A$1,1,SUMPRODUCT((--ISNUMBER(SEARCH("Q10.",'Data (paste export here)'!$A$1:$HZ$1)))*COLUMN('Data (paste export here)'!$A$1:$HZ$1))-1,10000,1),$A9,OFFSET('Data (paste export here)'!$B$1,1,0,10000,1),"<>") | C9: =IF(COUNTIF(OFFSET('Data (paste export here)'!$B$1,1,0,10000,1),"<>")=0,"",ROUND(B9/COUNTIF(OFFSET('Data (paste export here)'!$B$1,1,0,10000,1),"<>")*100,0))
A10: Other (please specify) | B10: =COUNTIFS(OFFSET('Data (paste export here)'!$A$1,1,SUMPRODUCT((--ISNUMBER(SEARCH("Q10.",'Data (paste export here)'!$A$1:$HZ$1)))*COLUMN('Data (paste export here)'!$A$1:$HZ$1))-1,10000,1),$A10,OFFSET('Data (paste export here)'!$B$1,1,0,10000,1),"<>") | C10: =IF(COUNTIF(OFFSET('Data (paste export here)'!$B$1,1,0,10000,1),"<>")=0,"",ROUND(B10/COUNTIF(OFFSET('Data (paste export here)'!$B$1,1,0,10000,1),"<>")*100,0))
A11: Unmatched (role not listed above — update the labels in A5:A10 if you edited Q10) | B11: =COUNTIFS(OFFSET('Data (paste export here)'!$A$1,1,SUMPRODUCT((--ISNUMBER(SEARCH("Q10.",'Data (paste export here)'!$A$1:$HZ$1)))*COLUMN('Data (paste export here)'!$A$1:$HZ$1))-1,10000,1),"<>",OFFSET('Data (paste export here)'!$B$1,1,0,10000,1),"<>")-SUM(B5:B10) | C11: =IF(COUNTIF(OFFSET('Data (paste export here)'!$B$1,1,0,10000,1),"<>")=0,"",ROUND(B11/COUNTIF(OFFSET('Data (paste export here)'!$B$1,1,0,10000,1),"<>")*100,0))
A12: Confidence (Q22)
A13: Answer | B13: Count | C13: %
A14: Not confident | B14: =COUNTIFS(OFFSET('Data (paste export here)'!$A$1,1,SUMPRODUCT((--ISNUMBER(SEARCH("Q22.",'Data (paste export here)'!$A$1:$HZ$1)))*COLUMN('Data (paste export here)'!$A$1:$HZ$1))-1,10000,1),$A14,OFFSET('Data (paste export here)'!$B$1,1,0,10000,1),"<>") | C14: =IF(COUNTIF(OFFSET('Data (paste export here)'!$B$1,1,0,10000,1),"<>")=0,"",ROUND(B14/COUNTIF(OFFSET('Data (paste export here)'!$B$1,1,0,10000,1),"<>")*100,0))
A15: Somewhat confident | B15: =COUNTIFS(OFFSET('Data (paste export here)'!$A$1,1,SUMPRODUCT((--ISNUMBER(SEARCH("Q22.",'Data (paste export here)'!$A$1:$HZ$1)))*COLUMN('Data (paste export here)'!$A$1:$HZ$1))-1,10000,1),$A15,OFFSET('Data (paste export here)'!$B$1,1,0,10000,1),"<>") | C15: =IF(COUNTIF(OFFSET('Data (paste export here)'!$B$1,1,0,10000,1),"<>")=0,"",ROUND(B15/COUNTIF(OFFSET('Data (paste export here)'!$B$1,1,0,10000,1),"<>")*100,0))
A16: Confident | B16: =COUNTIFS(OFFSET('Data (paste export here)'!$A$1,1,SUMPRODUCT((--ISNUMBER(SEARCH("Q22.",'Data (paste export here)'!$A$1:$HZ$1)))*COLUMN('Data (paste export here)'!$A$1:$HZ$1))-1,10000,1),$A16,OFFSET('Data (paste export here)'!$B$1,1,0,10000,1),"<>") | C16: =IF(COUNTIF(OFFSET('Data (paste export here)'!$B$1,1,0,10000,1),"<>")=0,"",ROUND(B16/COUNTIF(OFFSET('Data (paste export here)'!$B$1,1,0,10000,1),"<>")*100,0))
A17: Very confident | B17: =COUNTIFS(OFFSET('Data (paste export here)'!$A$1,1,SUMPRODUCT((--ISNUMBER(SEARCH("Q22.",'Data (paste export here)'!$A$1:$HZ$1)))*COLUMN('Data (paste export here)'!$A$1:$HZ$1))-1,10000,1),$A17,OFFSET('Data (paste export here)'!$B$1,1,0,10000,1),"<>") | C17: =IF(COUNTIF(OFFSET('Data (paste export here)'!$B$1,1,0,10000,1),"<>")=0,"",ROUND(B17/COUNTIF(OFFSET('Data (paste export here)'!$B$1,1,0,10000,1),"<>")*100,0))

Sheet Importance
A1: Importance of open source
A3: How important (Q20)
A4: Answer | B4: Count | C4: %
A5: Not important | B5: =COUNTIFS(OFFSET('Data (paste export here)'!$A$1,1,SUMPRODUCT((--ISNUMBER(SEARCH("Q20.",'Data (paste export here)'!$A$1:$HZ$1)))*COLUMN('Data (paste export here)'!$A$1:$HZ$1))-1,10000,1),$A5,OFFSET('Data (paste export here)'!$B$1,1,0,10000,1),"<>") | C5: =IF(COUNTIF(OFFSET('Data (paste export here)'!$B$1,1,0,10000,1),"<>")=0,"",ROUND(B5/COUNTIF(OFFSET('Data (paste export here)'!$B$1,1,0,10000,1),"<>")*100,0))
A6: Somewhat important | B6: =COUNTIFS(OFFSET('Data (paste export here)'!$A$1,1,SUMPRODUCT((--ISNUMBER(SEARCH("Q20.",'Data (paste export here)'!$A$1:$HZ$1)))*COLUMN('Data (paste export here)'!$A$1:$HZ$1))-1,10000,1),$A6,OFFSET('Data (paste export here)'!$B$1,1,0,10000,1),"<>") | C6: =IF(COUNTIF(OFFSET('Data (paste export here)'!$B$1,1,0,10000,1),"<>")=0,"",ROUND(B6/COUNTIF(OFFSET('Data (paste export here)'!$B$1,1,0,10000,1),"<>")*100,0))
A7: Important | B7: =COUNTIFS(OFFSET('Data (paste export here)'!$A$1,1,SUMPRODUCT((--ISNUMBER(SEARCH("Q20.",'Data (paste export here)'!$A$1:$HZ$1)))*COLUMN('Data (paste export here)'!$A$1:$HZ$1))-1,10000,1),$A7,OFFSET('Data (paste export here)'!$B$1,1,0,10000,1),"<>") | C7: =IF(COUNTIF(OFFSET('Data (paste export here)'!$B$1,1,0,10000,1),"<>")=0,"",ROUND(B7/COUNTIF(OFFSET('Data (paste export here)'!$B$1,1,0,10000,1),"<>")*100,0))
A8: Critical | B8: =COUNTIFS(OFFSET('Data (paste export here)'!$A$1,1,SUMPRODUCT((--ISNUMBER(SEARCH("Q20.",'Data (paste export here)'!$A$1:$HZ$1)))*COLUMN('Data (paste export here)'!$A$1:$HZ$1))-1,10000,1),$A8,OFFSET('Data (paste export here)'!$B$1,1,0,10000,1),"<>") | C8: =IF(COUNTIF(OFFSET('Data (paste export here)'!$B$1,1,0,10000,1),"<>")=0,"",ROUND(B8/COUNTIF(OFFSET('Data (paste export here)'!$B$1,1,0,10000,1),"<>")*100,0))
A9: I don't know | B9: =COUNTIFS(OFFSET('Data (paste export here)'!$A$1,1,SUMPRODUCT((--ISNUMBER(SEARCH("Q20.",'Data (paste export here)'!$A$1:$HZ$1)))*COLUMN('Data (paste export here)'!$A$1:$HZ$1))-1,10000,1),$A9,OFFSET('Data (paste export here)'!$B$1,1,0,10000,1),"<>") | C9: =IF(COUNTIF(OFFSET('Data (paste export here)'!$B$1,1,0,10000,1),"<>")=0,"",ROUND(B9/COUNTIF(OFFSET('Data (paste export here)'!$B$1,1,0,10000,1),"<>")*100,0))
A11: Why it matters (Q21, tick all that apply)
A12: Reason | B12: Count | C12: % of respondents
A13: Reduces vendor lock-in | B13: =COUNTIFS(OFFSET('Data (paste export here)'!$A$1,1,SUMPRODUCT((--ISNUMBER(SEARCH("Q21[SQ001]",'Data (paste export here)'!$A$1:$HZ$1)))*COLUMN('Data (paste export here)'!$A$1:$HZ$1))-1,10000,1),"Yes",OFFSET('Data (paste export here)'!$B$1,1,0,10000,1),"<>") | C13: =IF(COUNTIF(OFFSET('Data (paste export here)'!$B$1,1,0,10000,1),"<>")=0,"",ROUND(B13/COUNTIF(OFFSET('Data (paste export here)'!$B$1,1,0,10000,1),"<>")*100,0))
A14: Lowers costs | B14: =COUNTIFS(OFFSET('Data (paste export here)'!$A$1,1,SUMPRODUCT((--ISNUMBER(SEARCH("Q21[SQ002]",'Data (paste export here)'!$A$1:$HZ$1)))*COLUMN('Data (paste export here)'!$A$1:$HZ$1))-1,10000,1),"Yes",OFFSET('Data (paste export here)'!$B$1,1,0,10000,1),"<>") | C14: =IF(COUNTIF(OFFSET('Data (paste export here)'!$B$1,1,0,10000,1),"<>")=0,"",ROUND(B14/COUNTIF(OFFSET('Data (paste export here)'!$B$1,1,0,10000,1),"<>")*100,0))
A15: Enables collaboration across the research and education community | B15: =COUNTIFS(OFFSET('Data (paste export here)'!$A$1,1,SUMPRODUCT((--ISNUMBER(SEARCH("Q21[SQ003]",'Data (paste export here)'!$A$1:$HZ$1)))*COLUMN('Data (paste export here)'!$A$1:$HZ$1))-1,10000,1),"Yes",OFFSET('Data (paste export here)'!$B$1,1,0,10000,1),"<>") | C15: =IF(COUNTIF(OFFSET('Data (paste export here)'!$B$1,1,0,10000,1),"<>")=0,"",ROUND(B15/COUNTIF(OFFSET('Data (paste export here)'!$B$1,1,0,10000,1),"<>")*100,0))
A16: Supports transparency and trust | B16: =COUNTIFS(OFFSET('Data (paste export here)'!$A$1,1,SUMPRODUCT((--ISNUMBER(SEARCH("Q21[SQ004]",'Data (paste export here)'!$A$1:$HZ$1)))*COLUMN('Data (paste export here)'!$A$1:$HZ$1))-1,10000,1),"Yes",OFFSET('Data (paste export here)'!$B$1,1,0,10000,1),"<>") | C16: =IF(COUNTIF(OFFSET('Data (paste export here)'!$B$1,1,0,10000,1),"<>")=0,"",ROUND(B16/COUNTIF(OFFSET('Data (paste export here)'!$B$1,1,0,10000,1),"<>")*100,0))
A17: Accelerates innovation | B17: =COUNTIFS(OFFSET('Data (paste export here)'!$A$1,1,SUMPRODUCT((--ISNUMBER(SEARCH("Q21[SQ005]",'Data (paste export here)'!$A$1:$HZ$1)))*COLUMN('Data (paste export here)'!$A$1:$HZ$1))-1,10000,1),"Yes",OFFSET('Data (paste export here)'!$B$1,1,0,10000,1),"<>") | C17: =IF(COUNTIF(OFFSET('Data (paste export here)'!$B$1,1,0,10000,1),"<>")=0,"",ROUND(B17/COUNTIF(OFFSET('Data (paste export here)'!$B$1,1,0,10000,1),"<>")*100,0))
A18: Fulfils funder or regulatory requirements | B18: =COUNTIFS(OFFSET('Data (paste export here)'!$A$1,1,SUMPRODUCT((--ISNUMBER(SEARCH("Q21[SQ006]",'Data (paste export here)'!$A$1:$HZ$1)))*COLUMN('Data (paste export here)'!$A$1:$HZ$1))-1,10000,1),"Yes",OFFSET('Data (paste export here)'!$B$1,1,0,10000,1),"<>") | C18: =IF(COUNTIF(OFFSET('Data (paste export here)'!$B$1,1,0,10000,1),"<>")=0,"",ROUND(B18/COUNTIF(OFFSET('Data (paste export here)'!$B$1,1,0,10000,1),"<>")*100,0))
A19: Aligns with digital-sovereignty or institutional-autonomy goals | B19: =COUNTIFS(OFFSET('Data (paste export here)'!$A$1,1,SUMPRODUCT((--ISNUMBER(SEARCH("Q21[SQ007]",'Data (paste export here)'!$A$1:$HZ$1)))*COLUMN('Data (paste export here)'!$A$1:$HZ$1))-1,10000,1),"Yes",OFFSET('Data (paste export here)'!$B$1,1,0,10000,1),"<>") | C19: =IF(COUNTIF(OFFSET('Data (paste export here)'!$B$1,1,0,10000,1),"<>")=0,"",ROUND(B19/COUNTIF(OFFSET('Data (paste export here)'!$B$1,1,0,10000,1),"<>")*100,0))
A20: None — open source is not important to my work | B20: =COUNTIFS(OFFSET('Data (paste export here)'!$A$1,1,SUMPRODUCT((--ISNUMBER(SEARCH("Q21[SQ008]",'Data (paste export here)'!$A$1:$HZ$1)))*COLUMN('Data (paste export here)'!$A$1:$HZ$1))-1,10000,1),"Yes",OFFSET('Data (paste export here)'!$B$1,1,0,10000,1),"<>") | C20: =IF(COUNTIF(OFFSET('Data (paste export here)'!$B$1,1,0,10000,1),"<>")=0,"",ROUND(B20/COUNTIF(OFFSET('Data (paste export here)'!$B$1,1,0,10000,1),"<>")*100,0))

Sheet Maturity by area
A1: Maturity by area (Section 3)
A2: Average % of respondents reporting the practices in each area as in place.
A4: Area | B4: Maturity %
A5: Policy & OSPO | B5: =IFERROR(ROUND(AVERAGEIFS('Item results (auto)'!$F$2:$F$79,'Item results (auto)'!$K$2:$K$79,"Q300",'Item results (auto)'!$C$2:$C$79,"Maturity"),0),"")
A6: Compliance and risk | B6: =IFERROR(ROUND(AVERAGEIFS('Item results (auto)'!$F$2:$F$79,'Item results (auto)'!$K$2:$K$79,"Q310",'Item results (auto)'!$C$2:$C$79,"Maturity"),0),"")
A7: Security & supply chain | B7: =IFERROR(ROUND(AVERAGEIFS('Item results (auto)'!$F$2:$F$79,'Item results (auto)'!$K$2:$K$79,"Q320",'Item results (auto)'!$C$2:$C$79,"Maturity"),0),"")
A8: Selection, use & procurement | B8: =IFERROR(ROUND(AVERAGEIFS('Item results (auto)'!$F$2:$F$79,'Item results (auto)'!$K$2:$K$79,"Q330",'Item results (auto)'!$C$2:$C$79,"Maturity"),0),"")
A9: Open source contribution | B9: =IFERROR(ROUND(AVERAGEIFS('Item results (auto)'!$F$2:$F$79,'Item results (auto)'!$K$2:$K$79,"Q340",'Item results (auto)'!$C$2:$C$79,"Maturity"),0),"")
A10: Community and outreach | B10: =IFERROR(ROUND(AVERAGEIFS('Item results (auto)'!$F$2:$F$79,'Item results (auto)'!$K$2:$K$79,"Q350",'Item results (auto)'!$C$2:$C$79,"Maturity"),0),"")
A11: Hosting and maintenance | B11: =IFERROR(ROUND(AVERAGEIFS('Item results (auto)'!$F$2:$F$79,'Item results (auto)'!$K$2:$K$79,"Q360",'Item results (auto)'!$C$2:$C$79,"Maturity"),0),"")
A12: Leadership and strategy | B12: =IFERROR(ROUND(AVERAGEIFS('Item results (auto)'!$F$2:$F$79,'Item results (auto)'!$K$2:$K$79,"Q370",'Item results (auto)'!$C$2:$C$79,"Maturity"),0),"")

Sheet Experience & roles
A1: Community experience & roles (Section 5)
A2: Optional section. % is of all respondents.
A4: Ways people participate (Q52)
A5: Activity | B5: Count | C5: % of respondents
A6: Follow updates and discussions of open source projects | B6: =COUNTIFS(OFFSET('Data (paste export here)'!$A$1,1,SUMPRODUCT((--ISNUMBER(SEARCH("Q52[SQ001]",'Data (paste export here)'!$A$1:$HZ$1)))*COLUMN('Data (paste export here)'!$A$1:$HZ$1))-1,10000,1),"Yes",OFFSET('Data (paste export here)'!$B$1,1,0,10000,1),"<>") | C6: =IF(COUNTIF(OFFSET('Data (paste export here)'!$B$1,1,0,10000,1),"<>")=0,"",ROUND(B6/COUNTIF(OFFSET('Data (paste export here)'!$B$1,1,0,10000,1),"<>")*100,0))
A7: Use open source applications | B7: =COUNTIFS(OFFSET('Data (paste export here)'!$A$1,1,SUMPRODUCT((--ISNUMBER(SEARCH("Q52[SQ002]",'Data (paste export here)'!$A$1:$HZ$1)))*COLUMN('Data (paste export here)'!$A$1:$HZ$1))-1,10000,1),"Yes",OFFSET('Data (paste export here)'!$B$1,1,0,10000,1),"<>") | C7: =IF(COUNTIF(OFFSET('Data (paste export here)'!$B$1,1,0,10000,1),"<>")=0,"",ROUND(B7/COUNTIF(OFFSET('Data (paste export here)'!$B$1,1,0,10000,1),"<>")*100,0))
A8: Use open source dependencies in other projects | B8: =COUNTIFS(OFFSET('Data (paste export here)'!$A$1,1,SUMPRODUCT((--ISNUMBER(SEARCH("Q52[SQ003]",'Data (paste export here)'!$A$1:$HZ$1)))*COLUMN('Data (paste export here)'!$A$1:$HZ$1))-1,10000,1),"Yes",OFFSET('Data (paste export here)'!$B$1,1,0,10000,1),"<>") | C8: =IF(COUNTIF(OFFSET('Data (paste export here)'!$B$1,1,0,10000,1),"<>")=0,"",ROUND(B8/COUNTIF(OFFSET('Data (paste export here)'!$B$1,1,0,10000,1),"<>")*100,0))
A9: Participate in open source development (bugs, code, docs, maintenance, community) | B9: =COUNTIFS(OFFSET('Data (paste export here)'!$A$1,1,SUMPRODUCT((--ISNUMBER(SEARCH("Q52[SQ004]",'Data (paste export here)'!$A$1:$HZ$1)))*COLUMN('Data (paste export here)'!$A$1:$HZ$1))-1,10000,1),"Yes",OFFSET('Data (paste export here)'!$B$1,1,0,10000,1),"<>") | C9: =IF(COUNTIF(OFFSET('Data (paste export here)'!$B$1,1,0,10000,1),"<>")=0,"",ROUND(B9/COUNTIF(OFFSET('Data (paste export here)'!$B$1,1,0,10000,1),"<>")*100,0))
A10: None of the above | B10: =COUNTIFS(OFFSET('Data (paste export here)'!$A$1,1,SUMPRODUCT((--ISNUMBER(SEARCH("Q52[SQ005]",'Data (paste export here)'!$A$1:$HZ$1)))*COLUMN('Data (paste export here)'!$A$1:$HZ$1))-1,10000,1),"Yes",OFFSET('Data (paste export here)'!$B$1,1,0,10000,1),"<>") | C10: =IF(COUNTIF(OFFSET('Data (paste export here)'!$B$1,1,0,10000,1),"<>")=0,"",ROUND(B10/COUNTIF(OFFSET('Data (paste export here)'!$B$1,1,0,10000,1),"<>")*100,0))
A12: Contributor roles ever held (Q54)
A13: Role | B13: Count | C13: % of respondents
A14: Maintainer | B14: =COUNTIFS(OFFSET('Data (paste export here)'!$A$1,1,SUMPRODUCT((--ISNUMBER(SEARCH("Q54[SQ001]",'Data (paste export here)'!$A$1:$HZ$1)))*COLUMN('Data (paste export here)'!$A$1:$HZ$1))-1,10000,1),"Yes",OFFSET('Data (paste export here)'!$B$1,1,0,10000,1),"<>") | C14: =IF(COUNTIF(OFFSET('Data (paste export here)'!$B$1,1,0,10000,1),"<>")=0,"",ROUND(B14/COUNTIF(OFFSET('Data (paste export here)'!$B$1,1,0,10000,1),"<>")*100,0))
A15: Contributor | B15: =COUNTIFS(OFFSET('Data (paste export here)'!$A$1,1,SUMPRODUCT((--ISNUMBER(SEARCH("Q54[SQ002]",'Data (paste export here)'!$A$1:$HZ$1)))*COLUMN('Data (paste export here)'!$A$1:$HZ$1))-1,10000,1),"Yes",OFFSET('Data (paste export here)'!$B$1,1,0,10000,1),"<>") | C15: =IF(COUNTIF(OFFSET('Data (paste export here)'!$B$1,1,0,10000,1),"<>")=0,"",ROUND(B15/COUNTIF(OFFSET('Data (paste export here)'!$B$1,1,0,10000,1),"<>")*100,0))
A16: Bug / issue reporter | B16: =COUNTIFS(OFFSET('Data (paste export here)'!$A$1,1,SUMPRODUCT((--ISNUMBER(SEARCH("Q54[SQ003]",'Data (paste export here)'!$A$1:$HZ$1)))*COLUMN('Data (paste export here)'!$A$1:$HZ$1))-1,10000,1),"Yes",OFFSET('Data (paste export here)'!$B$1,1,0,10000,1),"<>") | C16: =IF(COUNTIF(OFFSET('Data (paste export here)'!$B$1,1,0,10000,1),"<>")=0,"",ROUND(B16/COUNTIF(OFFSET('Data (paste export here)'!$B$1,1,0,10000,1),"<>")*100,0))
A17: Supervisor | B17: =COUNTIFS(OFFSET('Data (paste export here)'!$A$1,1,SUMPRODUCT((--ISNUMBER(SEARCH("Q54[SQ004]",'Data (paste export here)'!$A$1:$HZ$1)))*COLUMN('Data (paste export here)'!$A$1:$HZ$1))-1,10000,1),"Yes",OFFSET('Data (paste export here)'!$B$1,1,0,10000,1),"<>") | C17: =IF(COUNTIF(OFFSET('Data (paste export here)'!$B$1,1,0,10000,1),"<>")=0,"",ROUND(B17/COUNTIF(OFFSET('Data (paste export here)'!$B$1,1,0,10000,1),"<>")*100,0))
A18: IT / systems administrator | B18: =COUNTIFS(OFFSET('Data (paste export here)'!$A$1,1,SUMPRODUCT((--ISNUMBER(SEARCH("Q54[SQ005]",'Data (paste export here)'!$A$1:$HZ$1)))*COLUMN('Data (paste export here)'!$A$1:$HZ$1))-1,10000,1),"Yes",OFFSET('Data (paste export here)'!$B$1,1,0,10000,1),"<>") | C18: =IF(COUNTIF(OFFSET('Data (paste export here)'!$B$1,1,0,10000,1),"<>")=0,"",ROUND(B18/COUNTIF(OFFSET('Data (paste export here)'!$B$1,1,0,10000,1),"<>")*100,0))
A19: UI / UX designer | B19: =COUNTIFS(OFFSET('Data (paste export here)'!$A$1,1,SUMPRODUCT((--ISNUMBER(SEARCH("Q54[SQ006]",'Data (paste export here)'!$A$1:$HZ$1)))*COLUMN('Data (paste export here)'!$A$1:$HZ$1))-1,10000,1),"Yes",OFFSET('Data (paste export here)'!$B$1,1,0,10000,1),"<>") | C19: =IF(COUNTIF(OFFSET('Data (paste export here)'!$B$1,1,0,10000,1),"<>")=0,"",ROUND(B19/COUNTIF(OFFSET('Data (paste export here)'!$B$1,1,0,10000,1),"<>")*100,0))
A20: Community manager | B20: =COUNTIFS(OFFSET('Data (paste export here)'!$A$1,1,SUMPRODUCT((--ISNUMBER(SEARCH("Q54[SQ007]",'Data (paste export here)'!$A$1:$HZ$1)))*COLUMN('Data (paste export here)'!$A$1:$HZ$1))-1,10000,1),"Yes",OFFSET('Data (paste export here)'!$B$1,1,0,10000,1),"<>") | C20: =IF(COUNTIF(OFFSET('Data (paste export here)'!$B$1,1,0,10000,1),"<>")=0,"",ROUND(B20/COUNTIF(OFFSET('Data (paste export here)'!$B$1,1,0,10000,1),"<>")*100,0))
A21: Technical support | B21: =COUNTIFS(OFFSET('Data (paste export here)'!$A$1,1,SUMPRODUCT((--ISNUMBER(SEARCH("Q54[SQ008]",'Data (paste export here)'!$A$1:$HZ$1)))*COLUMN('Data (paste export here)'!$A$1:$HZ$1))-1,10000,1),"Yes",OFFSET('Data (paste export here)'!$B$1,1,0,10000,1),"<>") | C21: =IF(COUNTIF(OFFSET('Data (paste export here)'!$B$1,1,0,10000,1),"<>")=0,"",ROUND(B21/COUNTIF(OFFSET('Data (paste export here)'!$B$1,1,0,10000,1),"<>")*100,0))
A22: Educator | B22: =COUNTIFS(OFFSET('Data (paste export here)'!$A$1,1,SUMPRODUCT((--ISNUMBER(SEARCH("Q54[SQ009]",'Data (paste export here)'!$A$1:$HZ$1)))*COLUMN('Data (paste export here)'!$A$1:$HZ$1))-1,10000,1),"Yes",OFFSET('Data (paste export here)'!$B$1,1,0,10000,1),"<>") | C22: =IF(COUNTIF(OFFSET('Data (paste export here)'!$B$1,1,0,10000,1),"<>")=0,"",ROUND(B22/COUNTIF(OFFSET('Data (paste export here)'!$B$1,1,0,10000,1),"<>")*100,0))
A23: None of the above | B23: =COUNTIFS(OFFSET('Data (paste export here)'!$A$1,1,SUMPRODUCT((--ISNUMBER(SEARCH("Q54[SQ010]",'Data (paste export here)'!$A$1:$HZ$1)))*COLUMN('Data (paste export here)'!$A$1:$HZ$1))-1,10000,1),"Yes",OFFSET('Data (paste export here)'!$B$1,1,0,10000,1),"<>") | C23: =IF(COUNTIF(OFFSET('Data (paste export here)'!$B$1,1,0,10000,1),"<>")=0,"",ROUND(B23/COUNTIF(OFFSET('Data (paste export here)'!$B$1,1,0,10000,1),"<>")*100,0))
